Workbook

Sheet Dashboard
A1: BENGALURU BBA FRESHER | JOB INTELLIGENCE CONTROL TOWER
A2: Research snapshot: 11 Oct 2026 | Candidate: BBA International Business | Bengaluru | CV-matched operations/procurement/supply chain/business support; non-sales roles prioritised.
A3: 43 core role records plus 1 newly validated official Accenture addendum. 506 employers are targets, not confirmed vacancies. Use Verified Openings and Verified Addendum; re-open every link before applying. Official requisition IDs and public job-board IDs are different.
A5: Researched role records (incl. addendum) | C5: Employer target universe | E5: P1 / highest priority leads | G5: Official requisition IDs captured | I5: Search sources / portals | K5: Role families mapped
A6: 44 | C6: 506 | E6: 10 | G6: 22 | I6: 24 | K6: 39
A9: Recommended workflow: (1) sort Apply Now by weighted score; (2) use Verified Addendum for the new official Accenture Supply Chain Operations req AIOC-S01665657; (3) open source and reconfirm Apply status; (4) ask recruiter for written fixed/variable CTC and benefit eligibility; (5) request referrals using exact official IDs; (6) update Application Tracker v2; (7) use Research Prompt v3 in new employer batches and record all checks.
A11: Company target sectors | B11: Company count
A12: IT Services, Consulting & BPO | B12: =COUNTIF('Company Universe'!$C$5:$C$510,A12)
A13: Banking, Financial Services & Insurance | B13: =COUNTIF('Company Universe'!$C$5:$C$510,A13)
A14: Global Technology, SaaS & GCCs | B14: =COUNTIF('Company Universe'!$C$5:$C$510,A14)
A15: Industrial, Manufacturing, Automotive & Energy | B15: =COUNTIF('Company Universe'!$C$5:$C$510,A15)
A16: Retail, E-commerce, Logistics, Travel & Hospitality | B16: =COUNTIF('Company Universe'!$C$5:$C$510,A16)
A17: Healthcare, Pharma, Biotech & Life Sciences | B17: =COUNTIF('Company Universe'!$C$5:$C$510,A17)
A18: Education, Media, Marketing & Professional Platforms | B18: =COUNTIF('Company Universe'!$C$5:$C$510,A18)
A19: Bengaluru Startups & Scaleups | B19: =COUNTIF('Company Universe'!$C$5:$C$510,A19)
A20: Public Sector, Infrastructure & Utilities | B20: =COUNTIF('Company Universe'!$C$5:$C$510,A20)

Sheet Live Jobs
A1: LEGACY SNAPSHOT – EARLIER JOB LEADS (NOT THE CURRENT RANKED LIST)
A2: Historical starter list from the initial database. Use the Verified Openings sheet for the current 43 researched leads and the Application Tracker v2 for execution. Recheck job status/IDs before applying.
A4: Record ID | B4: Status / Evidence | C4: Priority | D4: Company / Employer | E4: Role Title | F4: Role Family | G4: Employment Type | H4: Location | I4: Education / Degree | J4: Experience Requirement | K4: Salary (source wording) | L4: Posted Date / Age (source wording) | M4: Closing Date | N4: Official Requisition ID | O4: Public Listing ID | P4: ID Type / Interpretation | Q4: Source Platform | R4: Official Career / ATS URL | S4: Direct Apply / Listing URL | T4: Role Snapshot | U4: BBA / Fresher Fit Evidence | V4: Key Skills / Keywords | W4: Work Mode / Shift | X4: Risks / Verification Needed | Y4: Date Last Checked | Z4: Next Recheck Date | AA4: Application Status | AB4: Referral Status | AC4: Referrer / Contact Notes | AD4: Source Confidence
A5: JOB-0001 | B5: Recent official listing - recheck before referral | C5: P1 - apply first | D5: Accenture | E5: Procure-to-Pay Operations New Associate | F5: Finance operations / P2P | G5: Full-time | H5: Bengaluru | I5: Any graduation (official listing) | J5: 0-1 years | K5: Not disclosed | L5: Posted 8 days ago (as indexed) | M5: Not stated | N5: AIOC-S01664684 | P5: Official requisition ID | Q5: Official Accenture careers | R5: https://accenture.wd103.myworkdayjobs.com/accenturecareers/job/Bengaluru/Procure-to-Pay-Operations-New-Associate_AIOC-S01664684-1 | S5: https://accenture.wd103.myworkdayjobs.com/accenturecareers/job/Bengaluru/Procure-to-Pay-Operations-New-Associate_AIOC-S01664684-1 | T5: Invoice processing, procure-to-pay, purchase-order matching, vendor-payment and finance operations activities. | U5: 5/5 - direct BBA fresher-friendly fit if graduation is complete and shift acceptable. | V5: Excel; accuracy; invoice validation; data quality; documentation; process discipline | W5: Full-time; shift may be rotational | X5: Re-open official page and confirm Apply button/availability; ask referrer to use exact req ID. | Y5: 2026-10-11 | Z5: 2026-10-12 | AA5: Not Started | AB5: Not Contacted | AD5: Official page indexed as posted 8 days ago
A6: JOB-0002 | B6: Recent official listing - recheck before referral | C6: P1 - apply first | D6: Accenture | E6: Procurement Practice New Associate | F6: Procurement operations | G6: Full-time | H6: Bengaluru | I6: Any graduation (official listing) | J6: 0-1 years | K6: Not disclosed | L6: Posted 15 days ago (as indexed) | M6: Not stated | N6: AIOC-S01664045 | P6: Official requisition ID | Q6: Official Accenture careers | R6: https://accenture.wd103.myworkdayjobs.com/en-US/AccentureCareers/job/Bengaluru-BDC9A/Procurement-Practice-New-Associate_AIOC-S01664045-1 | S6: https://accenture.wd103.myworkdayjobs.com/en-US/AccentureCareers/job/Bengaluru-BDC9A/Procurement-Practice-New-Associate_AIOC-S01664045-1 | T6: Tactical and transactional procurement, supplier/catalog maintenance, trackers, audit coordination and procurement process support. | U6: 5/5 - strong degree and experience match based on official posting. | V6: Excel; supplier coordination; procurement basics; audit trail; reporting; communication | W6: Full-time; possible rotational shift | X6: Confirm the listing remains open and whether BBA is accepted under Any Graduation. | Y6: 2026-10-11 | Z6: 2026-10-12 | AA6: Not Started | AB6: Not Contacted | AD6: Official page indexed today; posted 15 days ago
A7: JOB-0003 | B7: Portal indexed - recheck freshness | C7: P1/P2 - check current status | D7: Accenture | E7: Procurement Operations New Associate | F7: Procurement operations | G7: Full-time | H7: Bengaluru | I7: BCom / Any Graduation / B.B.M shown on one official version | J7: 0-1 years | K7: Not disclosed | L7: Indexed about 2 weeks ago | M7: Not stated | N7: AIOC-S01660136 | P7: Official requisition ID | Q7: Official Accenture careers | R7: https://www.accenture.com/in-en/careers/jobdetails?id=AIOC-S01660136_en | S7: https://www.accenture.com/in-en/careers/jobdetails?id=AIOC-S01660136_en | T7: Procurement support, supplier setup, purchase processes, documentation, audit support and SLA reporting. | U7: 5/5 if the requisition is still accepting applications. | V7: Procurement; Excel; reporting; attention to detail; teamwork | W7: Full-time; possible rotational shift | X7: Re-open official page; multiple similar Accenture requisitions exist, so avoid duplicate referrals if already submitted. | Y7: 2026-10-11 | Z7: 2026-10-12 | AA7: Not Started | AB7: Not Contacted | AD7: Official result crawled recently; exact status must be reconfirmed
A8: JOB-0004 | B8: Official listing indexed - older, verify open/closed | C8: P2 - verify first | D8: Accenture | E8: Procure to Pay Operations New Associate | F8: Finance operations / P2P | G8: Full-time | H8: Bengaluru | I8: BCom / B.B.M (official listing) | J8: 0-1 years | K8: Not disclosed | L8: Posted 30+ days ago (indexed) | M8: Not stated | N8: AIOC-S01661384 | P8: Official requisition ID | Q8: Official Accenture careers | R8: https://accenture.wd103.myworkdayjobs.com/en-US/AccentureCareers/job/Bengaluru/Procure-to-Pay-Operations-New-Associate_AIOC-S01661384-1 | S8: https://accenture.wd103.myworkdayjobs.com/en-US/AccentureCareers/job/Bengaluru/Procure-to-Pay-Operations-New-Associate_AIOC-S01661384-1 | T8: Procure-to-pay and invoice processing role in finance operations. | U8: 4/5 - BBA may fit only if the role accepts B.B.M/related degree; confirm BBA is accepted. | V8: Invoice processing; Excel; data accuracy; vendor payment; documentation | W8: Full-time; possible rotational shift | X8: Older result. Confirm active status and BBA eligibility before referral. | Y8: 2026-10-11 | Z8: 2026-10-12 | AA8: Not Started | AB8: Not Contacted | AD8: Older official posting; do not treat as open until reconfirmed
A9: JOB-0005 | B9: Recent official listing - recheck before referral | C9: P1 - apply first | D9: EY | E9: Associate - Resource Management | F9: Workforce / business operations | G9: Full-time | H9: Bengaluru | I9: Degree requirements: review official JD | J9: 0-3 years reported; confirm exact requirement | K9: Competitive / not quantified | L9: 2026-10-08 | M9: Not stated | N9: 1739823 | P9: Official requisition ID | Q9: Official EY careers | R9: https://careers.ey.com/ey/job/Bengaluru-Associate-Resource-Management-KA-560048/1445690033/ | S9: https://careers.ey.com/ey/job/Bengaluru-Associate-Resource-Management-KA-560048/1445690033/ | T9: Resource scheduling, resource requests, utilisation reporting, stakeholder updates and resolving scheduling conflicts. | U9: 4/5 - good business coordination fit; verify BBA eligibility and Excel expectations. | V9: Advanced Excel; planning; data tracking; stakeholder management; reporting; prioritisation | W9: Full-time; location Bengaluru | X9: Official page dates the posting 8 Oct 2026; re-open role and confirm requirements before asking for referral. | Y9: 2026-10-11 | Z9: 2026-10-12 | AA9: Not Started | AB9: Not Contacted | AD9: Official posting dated 2026-10-08
A10: JOB-0006 | B10: Recent official ATS listing | C10: P1 - apply first | D10: Allegis Global Solutions | E10: Onboarding Associate - APAC Shift - Supply Chain / SCM | F10: Supplier onboarding / procurement operations | G10: Full-time | H10: Bengaluru; hybrid (Mon-Wed office noted) | I10: Bachelor's degree or related major/equivalent business experience | J10: Prior related experience is an advantage; internships/academic coordination can be considered | K10: Not disclosed | L10: Published date not disclosed; indexed yesterday | M10: Not stated | N10: 744000152372369 | O10: 4471701540 (LinkedIn listing reference from prior search) | P10: Official SmartRecruiters posting ID + public LinkedIn listing ID | Q10: Official SmartRecruiters / Allegis Global Solutions | R10: https://jobs.smartrecruiters.com/AllegisGlobalSolutions/744000152372369-onboarding-associate-apac-shift-supply-chain-scm-bengaluru | S10: https://jobs.smartrecruiters.com/AllegisGlobalSolutions/744000152372369-onboarding-associate-apac-shift-supply-chain-scm-bengaluru | T10: Supplier vetting/onboarding, document checking, compliance, trackers, reporting, escalations and cross-team coordination. | U10: 5/5 - coordination and documentation align well; internship/event coordination can help demonstrate stakeholder skills. | V10: Documentation; vendor follow-up; compliance; Excel; trackers; stakeholder communication; SLAs | W10: Hybrid; 10:00 AM-7:00 PM APAC shift shown | X10: Confirm current status and whether the LinkedIn ID points to this exact APAC variant before sending. | Y10: 2026-10-11 | Z10: 2026-10-12 | AA10: Not Started | AB10: Not Contacted | AD10: Official ATS page indexed yesterday
A11: JOB-0007 | B11: Recent official ATS listing | C11: P1/P2 - check shift preference | D11: Allegis Global Solutions | E11: Onboarding Associate - Meta (Global) - Supply Chain / SCM | F11: Supplier onboarding / procurement operations | G11: Full-time | H11: Bengaluru; hybrid | I11: Bachelor's degree or related major/equivalent business experience | J11: Relevant internship/academic coordination can be considered; prior experience an advantage | K11: Not disclosed | L11: Published date not disclosed; indexed today | M11: Not stated | N11: 744000151812601 | P11: Official SmartRecruiters posting ID | Q11: Official SmartRecruiters / Allegis Global Solutions | R11: https://jobs.smartrecruiters.com/allegisglobalsolutions/744000151812601 | S11: https://jobs.smartrecruiters.com/allegisglobalsolutions/744000151812601 | T11: Supplier onboarding and compliance; document collection, follow-ups, trackers, quality checks and process improvement. | U11: 4/5 - BBA-friendly coordination profile; later shift is the main consideration. | V11: Documentation; vendor coordination; Excel; data accuracy; compliance; written communication | W11: Hybrid; 3:00 PM-12:00 AM shift shown | X11: Confirm shift, posting status and exact live ID with employee. | Y11: 2026-10-11 | Z11: 2026-10-12 | AA11: Not Started | AB11: Not Contacted | AD11: Official ATS page indexed today
A12: JOB-0008 | B12: Third-party listing - fresher eligibility stated | C12: P1/P2 - refer after portal check | D12: JPMorgan Chase | E12: Business and Operations Specialist | F12: Business operations / vendor payments | G12: Full-time | H12: Bengaluru | I12: Review full listing; BBA eligibility not expressly verified in compact data | J12: Freshers can apply (public listing) | K12: Not disclosed | L12: Date not exposed in retrieved Apna data | M12: Not stated | N12: Not exposed | O12: 1129984729 | P12: Public Apna listing ID (not internal requisition) | Q12: Apna job board | R12: https://careers.jpmorgan.com/global/en | S12: https://apna.co/job/bengaluru-bangalore/business-and-operations-specialist-1129984729 | T12: Invoice validation, vendor-payment requests, mailbox monitoring, operational trackers, audit-ready records and issue resolution. | U12: 4/5 - business process work aligns well; verify exact degree requirement and that the role remains open. | V12: Excel; invoice checking; documentation; process adherence; query handling; detail orientation | W12: Full-time; exact shift not verified | X12: Ask employee to find this title or equivalent on JPMC's internal careers portal; do not use the Apna ID as a JPMC requisition. | Y12: 2026-10-11 | Z12: 2026-10-12 | AA12: Not Started | AB12: Not Contacted | AD12: Job-board indexed; official requisition/status unknown
A13: JOB-0009 | B13: Third-party listing - fresher-only stated | C13: P1 - apply after status check | D13: Marriott International / Marriott Hotels India | E13: Purchase Associate | F13: Purchasing / hotel operations | G13: Full-time | H13: Bengaluru | I13: Confirm exact degree requirements in full JD | J13: Freshers only (Apna listing) | K13: Not disclosed | L13: Date not exposed in retrieved Apna data | M13: Not stated | N13: Not exposed | O13: 1912459795 | P13: Public Apna listing ID (not internal requisition) | Q13: Apna job board | R13: https://careers.marriott.com/ | S13: https://apna.co/job/bengaluru-bangalore/purchase-associate-1912459795 | T13: Inventory and order records, invoices, requisitions, stock monitoring, receiving reports and supplier-delivery issue follow-up. | U13: 4/5 - purchasing and operations are direct BBA-adjacent functions; hospitality shift/physical duties may apply. | V13: Inventory; Excel; invoice reconciliation; purchase requisitions; vendor follow-up; recordkeeping | W13: On-site likely; confirm with employer | X13: Search Marriott's official portal for the same role/location; confirm the Apna listing still exists. | Y13: 2026-10-11 | Z13: 2026-10-12 | AA13: Not Started | AB13: Not Contacted | AD13: Job-board indexed; official requisition/status unknown
A14: JOB-0010 | B14: Third-party listing - fresher eligibility stated | C14: P1/P2 - refer after verification | D14: KPMG India Services | E14: Business Associate - Quality and Risk Management | F14: Risk / quality / research operations | G14: Full-time | H14: Bengaluru | I14: Full degree/field requirements need full JD review | J14: Freshers can apply (Apna listing) | K14: Not disclosed | L14: Date not exposed in retrieved Apna data | M14: Not stated | N14: Not exposed | O14: 1779532141 | P14: Public Apna listing ID (not internal requisition) | Q14: Apna job board | R14: https://kpmg.com/in/en/home/careers.html | S14: https://apna.co/job/bengaluru-bangalore/business-associate-quality-and-risk-management-1779532141 | T14: Corporate/database research, regulatory and risk checks, research databases, offshore stakeholder updates and project execution. | U14: 4/5 - good fit if BBA is accepted and candidate can show research, documentation and professional communication. | V14: Online research; Excel; written communication; risk awareness; attention to detail; reporting | W14: Full-time; possible international team schedule | X14: Find matching posting on official KPMG portal or confirm with employee; public job-board ID is not an internal requisition. | Y14: 2026-10-11 | Z14: 2026-10-12 | AA14: Not Started | AB14: Not Contacted | AD14: Job-board indexed; official requisition/status unknown
A15: JOB-0011 | B15: Third-party listing - fresher-only stated | C15: P2 - review full JD | D15: Altisource | E15: Associate (Granite) | F15: Business / financial operations | G15: Full-time | H15: Bengaluru | I15: Not fully confirmed in compact listing | J15: Freshers only (Apna listing) | K15: Not disclosed | L15: Date not exposed in retrieved Apna data | M15: Not stated | N15: Not exposed | O15: 1340046698 | P15: Public Apna listing ID (not internal requisition) | Q15: Apna job board | R15: https://www.altisource.com/careers | S15: https://apna.co/job/bengaluru-bangalore/associate-1340046698 | T15: Listing describes executive-facing work organizing financial strategy for business lines; inspect role scope closely. | U15: 3/5 - possible business role, but specific analytical/financial requirements need a careful check. | V15: Excel; financial/operational analysis; documentation; communication | W15: Confirm with employer | X15: Confirm the exact degree, work scope and active status from official employer channel. | Y15: 2026-10-11 | Z15: 2026-10-12 | AA15: Not Started | AB15: Not Contacted | AD15: Job-board indexed; eligibility and official req unknown
A16: JOB-0012 | B16: Third-party listing - fresher-only internship | C16: P2 - internship pathway | D16: Pearson | E16: HR Operations Associate Intern | F16: HR operations / people services | G16: Internship | H16: Bengaluru; Cunningham Road listed | I16: Review full official JD | J16: Freshers only (Apna listing) | K16: Not disclosed | L16: Date not exposed in retrieved Apna data | M16: Not stated | N16: Not exposed | O16: 1682511397 | P16: Public Apna listing ID (not internal requisition) | Q16: Apna job board | R16: https://pearson.jobs/ | S16: https://apna.co/job/bengaluru-bangalore/hr-operations-associate-intern-1682511397 | T16: Internship supports HR operations and real projects; source displayed an unusual duration field, which needs checking. | U16: 4/5 - good bridge into HR operations if internship duration and stipend work for you. | V16: Excel; employee data handling; HR administration; confidentiality; coordination | W16: Likely on-site; verify | X16: Check stipend, duration and whether this is an active requisition on Pearson's own career portal. | Y16: 2026-10-11 | Z16: 2026-10-12 | AA16: Not Started | AB16: Not Contacted | AD16: Job-board indexed; duration field inconsistent/verify
A17: JOB-0013 | B17: Third-party listing - apprenticeship | C17: P2 - structured entry path | D17: Deutsche Bank | E17: Human Resources Apprentice (2026-2027) | F17: HR operations / apprenticeship | G17: 12-month apprenticeship | H17: Bengaluru; listing also names Mumbai and Pune | I17: Check official apprenticeship eligibility and passing-year rules | J17: Freshers only (Apna listing) | K17: Not disclosed in retrieved listing | L17: Date not exposed in retrieved Apna data | M17: Not stated | N17: Not exposed | O17: 1125222884 | P17: Public Apna listing ID (not internal requisition) | Q17: Apna job board | R17: https://careers.db.com/professionals/search-roles/ | S17: https://apna.co/job/bengaluru-bangalore/human-resources-apprentice-1125222884 | T17: 12-month apprenticeship with structured on-the-job HR learning; source says permanent employment is not guaranteed afterward. | U17: 4/5 - relevant to BBA if the programme accepts your batch, degree and apprenticeship eligibility. | V17: HR administration; communication; Excel; confidentiality; coordination | W17: Full-time apprenticeship; confirm in-office requirements | X17: Check age/batch/NATS eligibility, stipend and active official role. Not a guaranteed permanent job. | Y17: 2026-10-11 | Z17: 2026-10-12 | AA17: Not Started | AB17: Not Contacted | AD17: Public listing indexed; official req/status unknown
A18: JOB-0014 | B18: Third-party listing - fresher-only internship | C18: P2 - internship pathway | D18: Intugine Technologies | E18: Operations Intern - Reverse Logistics | F18: Logistics / operations / supply chain | G18: Internship | H18: Bengaluru | I18: Not fully specified in compact listing | J18: Freshers only (Apna listing) | K18: Not disclosed | L18: Date not exposed in retrieved Apna data | M18: Not stated | N18: Not exposed | O18: 1694554752 | P18: Public Apna listing ID (not internal requisition) | Q18: Apna job board | R18: https://intugine.com/careers/ | S18: https://apna.co/job/bengaluru-bangalore/operations-intern-reverse-logistics-1694554752 | T18: Supports reverse-logistics and supply-chain operations; useful path into logistics-tech and operations. | U18: 4/5 - good relevant exposure if stipend and timing are suitable. | V18: Operations coordination; Excel; data tracking; logistics; problem solving | W18: Confirm with employer | X18: Confirm active status, duration, stipend and possible full-time conversion. | Y18: 2026-10-11 | Z18: 2026-10-12 | AA18: Not Started | AB18: Not Contacted | AD18: Job-board indexed; official requisition/status unknown
A19: JOB-0015 | B19: Freshly indexed third-party listing | C19: P1 - apply now after quick check | D19: SharePal | E19: Associate - Purchase - Fresher | F19: Purchasing / procurement | G19: Full-time | H19: Bengaluru | I19: Review employer's JD | J19: No experience required | K19: ₹4,00,000-₹5,00,000/year listed | L19: Posted 1 week ago | M19: Not stated | N19: Not exposed | O19: 1790684619 (embedded in Internshala URL) | P19: Public Internshala listing reference; not an internal requisition | Q19: Internshala | R19: https://www.google.com/search?q=SharePal+official+careers+Bengaluru | S19: https://internshala.com/job/detail/fresher-associate-purchase-job-in-bangalore-at-sharepal1790684619/ | T19: Entry-level purchase associate role in Bengaluru; source indicated no experience required and ₹4-5 LPA. | U19: 5/5 - strong fit for procurement/purchasing preferences, subject to requirements and job still open. | V19: Purchase coordination; Excel; vendor follow-up; communication; documentation | W19: Confirm on listing | X19: 242 applicants were shown when indexed; apply quickly and verify company legitimacy, role details and application deadline. | Y19: 2026-10-11 | Z19: 2026-10-12 | AA19: Not Started | AB19: Not Contacted | AD19: Posted about 1 week ago on Internshala
A20: JOB-0016 | B20: Recent third-party listing | C20: P1/P2 - verify call-based elements | D20: Nathaniel School of Music | E20: Student Support & Operations Executive - Fresher | F20: Education / student operations | G20: Full-time | H20: Bengaluru | I20: BBA-compatible on face of title; verify JD | J20: No experience required | K20: ₹3,60,000-₹4,20,000/year listed | L20: Posted 1 week ago | M20: Not stated | N20: Not exposed | O20: 1790600518 (embedded in Internshala URL) | P20: Public Internshala listing reference | Q20: Internshala | R20: https://www.google.com/search?q=Nathaniel+School+of+Music+careers | S20: https://internshala.com/job/detail/fresher-student-support-operations-executive-job-in-bangalore-at-nathaniel-school-of-music1790600518/ | T20: Student support and operations work in an education organisation. | U20: 4/5 - communication and coordination experience is relevant; assess voice/call responsibilities before applying. | V20: Student/customer operations; scheduling; communication; documentation; issue resolution | W20: Confirm with employer | X20: Review job description, role's call-based component, exact hours and salary structure. | Y20: 2026-10-11 | Z20: 2026-10-12 | AA20: Not Started | AB20: Not Contacted | AD20: Posted about 1 week ago on Internshala
A21: JOB-0017 | B21: Recent third-party listing | C21: P2 - verify scope | D21: Nathaniel School of Music | E21: Operations & Admin Executive (Education) - Fresher | F21: Administration / education operations | G21: Full-time | H21: Bengaluru | I21: BBA-compatible on face of title; verify JD | J21: No experience required | K21: ₹3,00,000-₹4,20,000/year listed | L21: Posted 5 days ago | M21: Not stated | N21: Not exposed | O21: 1791182216 (embedded in Internshala URL) | P21: Public Internshala listing reference | Q21: Internshala | R21: https://www.google.com/search?q=Nathaniel+School+of+Music+careers | S21: https://internshala.com/job/detail/fresher-operations-admin-executive-education-job-in-bangalore-at-nathaniel-school-of-music1791182216/ | T21: Operations and administrative support for an education organisation. | U21: 4/5 - event coordination, team supervision and documentation can be framed as relevant experience. | V21: Administrative operations; scheduling; recordkeeping; Excel; communication | W21: Confirm with employer | X21: Verify role scope, employer details, compensation structure and whether there are sales targets. | Y21: 2026-10-11 | Z21: 2026-10-12 | AA21: Not Started | AB21: Not Contacted | AD21: Posted about 5 days ago on Internshala
A22: JOB-0018 | B22: Recent third-party listing - role scope check | C22: P3 - verify title/scope carefully | D22: Soul Staje | E22: Operations Manager - Fresher | F22: Operations | G22: Full-time | H22: Bengaluru | I22: Review full listing | J22: No experience required listed | K22: ₹2,60,000-₹3,90,000/year listed | L22: Posted 1 day ago | M22: Not stated | N22: Not exposed | O22: 1791557235 (embedded in Internshala URL) | P22: Public Internshala listing reference | Q22: Internshala | R22: https://www.google.com/search?q=Soul+Staje+official+careers | S22: https://internshala.com/job/detail/fresher-operations-manager-job-in-bangalore-at-soul-staje1791557235/ | T22: Title says Operations Manager but listing is tagged fresher; likely needs detailed scope verification. | U22: 2/5 - title and fresher tag are unusual; compare actual responsibilities before investing time. | V22: Operations coordination; process tracking; communication | W22: Confirm with employer | X22: Treat as lower confidence until employer identity, manager scope, salary and reporting line are confirmed. | Y22: 2026-10-11 | Z22: 2026-10-12 | AA22: Not Started | AB22: Not Contacted | AD22: Posted about 1 day ago on Internshala
A23: JOB-0019 | B23: Third-party listing - older, recheck open/closed | C23: P2 - recheck status | D23: Prosperr.io | E23: Operation Support Associate | F23: Business operations / customer operations | G23: Full-time | H23: Bengaluru | I23: Bachelor's degree may be suitable; confirm full JD | J23: Freshers and 0-3 years described in listing/search context | K23: ₹3 LPA onwards previously indexed; confirm current listing | L23: 2026-09-12 | M23: Not stated | N23: Not exposed | O23: JOBSEARCH_100681 (Indeed internal result ref, not public requisition) | P23: Indeed result reference; no public requisition ID exposed | Q23: Indeed | R23: https://www.google.com/search?q=Prosperr.io+careers+Bengaluru | S23: https://to.indeed.com/aacxlw2cqb9c | T23: Operational data, reports, dashboards, customer operations support and cross-team coordination. | U23: 4/5 - likely good operations path, but the listing is around a month old. | V23: Excel/Google Sheets; reporting; dashboards; coordination; written communication | W23: Confirm with employer | X23: Open listing and confirm still active before referral; do not treat Indeed result key as a company job ID. | Y23: 2026-10-11 | Z23: 2026-10-12 | AA23: Not Started | AB23: Not Contacted | AD23: Posted 2026-09-12; stale until reconfirmed
... A27: JOB-0023 | B27: Recent third-party listing - role match possible | C27: P2 - verify experience | D27: NITSHAW | E27: Service and Purchase Coordinator | F27: Purchasing / service operations | G27: Full-time (verify) | H27: Bengaluru | I27: Not exposed in compact listing | J27: Not confirmed | K27: Not exposed | L27: 2026-09-21 | M27: Not stated | N27: Not exposed | O27: JOBSEARCH_100693 (Indeed internal result ref, not public requisition) | P27: Indeed result reference; no public requisition ID exposed | Q27: Indeed | R27: https://www.google.com/search?q=NITSHAW+careers+Bengaluru | S27: https://to.indeed.com/aamp4t7ygf72 | T27: Service operations and purchase coordination, potentially relevant to vendor follow-up and documentation experience. | U27: 3/5 - consider only after checking qualifications and whether fresher applications are accepted. | V27: Purchase coordination; vendor follow-up; documentation; service operations | W27: Confirm on-site/hybrid | X27: Listing posted in September; check if still open and obtain full JD. | Y27: 2026-10-11 | Z27: 2026-10-12 | AA27: Not Started | AB27: Not Contacted | AD27: Posted 2026-09-21; reconfirm

Sheet Company Universe
A1: BENGALURU COMPANY TARGET UNIVERSE | 500+ EMPLOYERS
A2: A broad prospecting universe across MNCs, GCCs, Indian enterprises, financial services, industrials and startups. Each row is a company target, not evidence of an active vacancy or verified local office.
A4: Company ID | B4: Company Name | C4: Sector | D4: Employer Type / Segment | E4: Bengaluru Footprint Confidence | F4: Fortune / Enterprise Classification | G4: BBA-Friendly Role Families to Search | H4: Target Priority | I4: Career Portal / Discovery URL | J4: URL Type | K4: Bengaluru Role Search Shortcut | L4: Vacancy Evidence Status | M4: Last Portal Check | N4: ATS / Platform if known | O4: Next Search Plan | P4: Research Notes
A5: CO-0001 | B5: Accenture | C5: IT Services, Consulting & BPO | D5: MNC / professional services | E5: Strong or plausible Bengaluru hiring ecosystem; verify role location | F5: Fortune-scale global enterprise / likely annual-list candidate; verify exact current list & rank | G5: Business operations; process associate; PMO; procurement; finance operations; HR operations; workforce coordination; client/service delivery support; research; digital marketing operations | H5: P1 - start here | I5: https://www.accenture.com/in-en/careers | J5: Official careers page | K5: https://www.google.com/search?q=Accenture+Bengaluru+Bangalore+entry+level+careers+operations+procurement+HR+jobs | L5: Company target only - no current vacancy independently verified in company-universe scan | M5: Not checked in this build | O5: Re-check every 7 days; check official portal first, then ATS / LinkedIn / job boards | P5: Company target only; this row is not proof of a live vacancy. Search exact Bengaluru location, filter by 0-2 years and degree eligibility, then record a verified requisition in Live Jobs.
A6: CO-0002 | B6: Capgemini | C6: IT Services, Consulting & BPO | D6: MNC / professional services | E6: Strong or plausible Bengaluru hiring ecosystem; verify role location | F6: Global enterprise; check latest Fortune US 500 / Global 500 / 1000 lists | G6: Business operations; process associate; PMO; procurement; finance operations; HR operations; workforce coordination; client/service delivery support; research; digital marketing operations | H6: P1 | I6: https://www.capgemini.com/in-en/careers/ | J6: Official careers page | K6: https://www.google.com/search?q=Capgemini+Bengaluru+Bangalore+entry+level+careers+operations+procurement+HR+jobs | L6: Company target only - no current vacancy independently verified in company-universe scan | M6: Not checked in this build | O6: Re-check every 7 days; check official portal first, then ATS / LinkedIn / job boards | P6: Company target only; this row is not proof of a live vacancy. Search exact Bengaluru location, filter by 0-2 years and degree eligibility, then record a verified requisition in Live Jobs.
A7: CO-0003 | B7: Tata Consultancy Services (TCS) | C7: IT Services, Consulting & BPO | D7: MNC / professional services | E7: Strong or plausible Bengaluru hiring ecosystem; verify role location | F7: Global enterprise; check latest Fortune US 500 / Global 500 / 1000 lists | G7: Business operations; process associate; PMO; procurement; finance operations; HR operations; workforce coordination; client/service delivery support; research; digital marketing operations | H7: P1 | I7: https://www.tcs.com/careers | J7: Official careers page | K7: https://www.google.com/search?q=Tata+Consultancy+Services+%28TCS%29+Bengaluru+Bangalore+entry+level+careers+operations+procurement+HR+jobs | L7: Company target only - no current vacancy independently verified in company-universe scan | M7: Not checked in this build | O7: Re-check every 7 days; check official portal first, then ATS / LinkedIn / job boards | P7: Company target only; this row is not proof of a live vacancy. Search exact Bengaluru location, filter by 0-2 years and degree eligibility, then record a verified requisition in Live Jobs.
A8: CO-0004 | B8: Infosys | C8: IT Services, Consulting & BPO | D8: MNC / professional services | E8: Strong or plausible Bengaluru hiring ecosystem; verify role location | F8: Global enterprise; check latest Fortune US 500 / Global 500 / 1000 lists | G8: Business operations; process associate; PMO; procurement; finance operations; HR operations; workforce coordination; client/service delivery support; research; digital marketing operations | H8: P1 | I8: https://www.infosys.com/careers/ | J8: Official careers page | K8: https://www.google.com/search?q=Infosys+Bengaluru+Bangalore+entry+level+careers+operations+procurement+HR+jobs | L8: Company target only - no current vacancy independently verified in company-universe scan | M8: Not checked in this build | O8: Re-check every 7 days; check official portal first, then ATS / LinkedIn / job boards | P8: Company target only; this row is not proof of a live vacancy. Search exact Bengaluru location, filter by 0-2 years and degree eligibility, then record a verified requisition in Live Jobs.
A9: CO-0005 | B9: Wipro | C9: IT Services, Consulting & BPO | D9: MNC / professional services | E9: Strong or plausible Bengaluru hiring ecosystem; verify role location | F9: Global enterprise; check latest Fortune US 500 / Global 500 / 1000 lists | G9: Business operations; process associate; PMO; procurement; finance operations; HR operations; workforce coordination; client/service delivery support; research; digital marketing operations | H9: P1 | I9: https://careers.wipro.com/ | J9: Official careers page | K9: https://www.google.com/search?q=Wipro+Bengaluru+Bangalore+entry+level+careers+operations+procurement+HR+jobs | L9: Company target only - no current vacancy independently verified in company-universe scan | M9: Not checked in this build | O9: Re-check every 7 days; check official portal first, then ATS / LinkedIn / job boards | P9: Company target only; this row is not proof of a live vacancy. Search exact Bengaluru location, filter by 0-2 years and degree eligibility, then record a verified requisition in Live Jobs.
A10: CO-0006 | B10: Cognizant | C10: IT Services, Consulting & BPO | D10: MNC / professional services | E10: Strong or plausible Bengaluru hiring ecosystem; verify role location | F10: Global enterprise; check latest Fortune US 500 / Global 500 / 1000 lists | G10: Business operations; process associate; PMO; procurement; finance operations; HR operations; workforce coordination; client/service delivery support; research; digital marketing operations | H10: P1 | I10: https://careers.cognizant.com/india-en/ | J10: Official careers page | K10: https://www.google.com/search?q=Cognizant+Bengaluru+Bangalore+entry+level+careers+operations+procurement+HR+jobs | L10: Company target only - no current vacancy independently verified in company-universe scan | M10: Not checked in this build | O10: Re-check every 7 days; check official portal first, then ATS / LinkedIn / job boards | P10: Company target only; this row is not proof of a live vacancy. Search exact Bengaluru location, filter by 0-2 years and degree eligibility, then record a verified requisition in Live Jobs.
A11: CO-0007 | B11: HCLTech | C11: IT Services, Consulting & BPO | D11: MNC / professional services | E11: Strong or plausible Bengaluru hiring ecosystem; verify role location | F11: Global enterprise; check latest Fortune US 500 / Global 500 / 1000 lists | G11: Business operations; process associate; PMO; procurement; finance operations; HR operations; workforce coordination; client/service delivery support; research; digital marketing operations | H11: P1 | I11: https://www.hcltech.com/careers | J11: Official careers page | K11: https://www.google.com/search?q=HCLTech+Bengaluru+Bangalore+entry+level+careers+operations+procurement+HR+jobs | L11: Company target only - no current vacancy independently verified in company-universe scan | M11: Not checked in this build | O11: Re-check every 7 days; check official portal first, then ATS / LinkedIn / job boards | P11: Company target only; this row is not proof of a live vacancy. Search exact Bengaluru location, filter by 0-2 years and degree eligibility, then record a verified requisition in Live Jobs.
A12: CO-0008 | B12: Tech Mahindra | C12: IT Services, Consulting & BPO | D12: MNC / professional services | E12: Strong or plausible Bengaluru hiring ecosystem; verify role location | F12: Global enterprise; check latest Fortune US 500 / Global 500 / 1000 lists | G12: Business operations; process associate; PMO; procurement; finance operations; HR operations; workforce coordination; client/service delivery support; research; digital marketing operations | H12: P1 | I12: https://www.techmahindra.com/careers/ | J12: Official careers page | K12: https://www.google.com/search?q=Tech+Mahindra+Bengaluru+Bangalore+entry+level+careers+operations+procurement+HR+jobs | L12: Company target only - no current vacancy independently verified in company-universe scan | M12: Not checked in this build | O12: Re-check every 7 days; check official portal first, then ATS / LinkedIn / job boards | P12: Company target only; this row is not proof of a live vacancy. Search exact Bengaluru location, filter by 0-2 years and degree eligibility, then record a verified requisition in Live Jobs.
A13: CO-0009 | B13: LTIMindtree | C13: IT Services, Consulting & BPO | D13: MNC / professional services | E13: Strong or plausible Bengaluru hiring ecosystem; verify role location | F13: Global enterprise; check latest Fortune US 500 / Global 500 / 1000 lists | G13: Business operations; process associate; PMO; procurement; finance operations; HR operations; workforce coordination; client/service delivery support; research; digital marketing operations | H13: P1 | I13: https://www.ltimindtree.com/careers/ | J13: Official careers page | K13: https://www.google.com/search?q=LTIMindtree+Bengaluru+Bangalore+entry+level+careers+operations+procurement+HR+jobs | L13: Company target only - no current vacancy independently verified in company-universe scan | M13: Not checked in this build | O13: Re-check every 7 days; check official portal first, then ATS / LinkedIn / job boards | P13: Company target only; this row is not proof of a live vacancy. Search exact Bengaluru location, filter by 0-2 years and degree eligibility, then record a verified requisition in Live Jobs.
A14: CO-0010 | B14: Mphasis | C14: IT Services, Consulting & BPO | D14: MNC / professional services | E14: Strong or plausible Bengaluru hiring ecosystem; verify role location | F14: Global enterprise; check latest Fortune US 500 / Global 500 / 1000 lists | G14: Business operations; process associate; PMO; procurement; finance operations; HR operations; workforce coordination; client/service delivery support; research; digital marketing operations | H14: P1 | I14: https://careers.mphasis.com/ | J14: Official careers page | K14: https://www.google.com/search?q=Mphasis+Bengaluru+Bangalore+entry+level+careers+operations+procurement+HR+jobs | L14: Company target only - no current vacancy independently verified in company-universe scan | M14: Not checked in this build | O14: Re-check every 7 days; check official portal first, then ATS / LinkedIn / job boards | P14: Company target only; this row is not proof of a live vacancy. Search exact Bengaluru location, filter by 0-2 years and degree eligibility, then record a verified requisition in Live Jobs.
A15: CO-0011 | B15: Genpact | C15: IT Services, Consulting & BPO | D15: MNC / professional services | E15: Strong or plausible Bengaluru hiring ecosystem; verify role location | F15: Global enterprise; check latest Fortune US 500 / Global 500 / 1000 lists | G15: Business operations; process associate; PMO; procurement; finance operations; HR operations; workforce coordination; client/service delivery support; research; digital marketing operations | H15: P1 - start here | I15: https://www.genpact.com/careers | J15: Official careers page | K15: https://www.google.com/search?q=Genpact+Bengaluru+Bangalore+entry+level+careers+operations+procurement+HR+jobs | L15: Company target only - no current vacancy independently verified in company-universe scan | M15: Not checked in this build | O15: Re-check every 7 days; check official portal first, then ATS / LinkedIn / job boards | P15: Company target only; this row is not proof of a live vacancy. Search exact Bengaluru location, filter by 0-2 years and degree eligibility, then record a verified requisition in Live Jobs.
A16: CO-0012 | B16: Concentrix | C16: IT Services, Consulting & BPO | D16: MNC / professional services | E16: Strong or plausible Bengaluru hiring ecosystem; verify role location | F16: Global enterprise; check latest Fortune US 500 / Global 500 / 1000 lists | G16: Business operations; process associate; PMO; procurement; finance operations; HR operations; workforce coordination; client/service delivery support; research; digital marketing operations | H16: P1 | I16: https://jobs.concentrix.com/global/en | J16: Official careers page | K16: https://www.google.com/search?q=Concentrix+Bengaluru+Bangalore+entry+level+careers+operations+procurement+HR+jobs | L16: Company target only - no current vacancy independently verified in company-universe scan | M16: Not checked in this build | O16: Re-check every 7 days; check official portal first, then ATS / LinkedIn / job boards | P16: Company target only; this row is not proof of a live vacancy. Search exact Bengaluru location, filter by 0-2 years and degree eligibility, then record a verified requisition in Live Jobs.
... A510: CO-0506 | B510: SIDBI | C510: Public Sector, Infrastructure & Utilities | D510: Public sector / infrastructure | E510: Regional/national employer; confirm Bengaluru-specific site or role | F510: Indian enterprise / public-sector target; not a Fortune claim | G510: Operations support; procurement; admin; project coordination; vendor management; documentation; HR; finance/accounts operations; apprenticeships and graduate trainee roles | H510: P2 | I510: https://www.google.com/search?q=SIDBI+official+careers+Bengaluru+jobs | J510: Search shortcut - verify official portal | K510: https://www.google.com/search?q=SIDBI+Bengaluru+Bangalore+entry+level+careers+operations+procurement+HR+jobs | L510: Company target only - no current vacancy independently verified in company-universe scan | M510: Not checked in this build | O510: Re-check every 7 days; check official portal first, then ATS / LinkedIn / job boards | P510: Company target only; this row is not proof of a live vacancy. Search exact Bengaluru location, filter by 0-2 years and degree eligibility, then record a verified requisition in Live Jobs. Careers URL is a search shortcut, not the employer's own portal.

Sheet Role Taxonomy
A1: ROLE TAXONOMY | BBA-FRIENDLY NON-SALES PATHWAYS
A2: Use these families to generate separate, precise searches. Eligibility is role-specific; verify every job description.
A4: Role Family / Title | B4: Priority | C4: Typical Entry Eligibility | D4: Core Responsibilities | E4: Search Title Variants | F4: Likely Skills / Keywords | G4: Fit for Candidate Preference | H4: Screening Notes
A5: Business Operations Associate | B5: P1 | C5: BBA/any graduation; 0-2 years | D5: Process tracking, dashboards, cross-functional coordination, SOPs, issue handling | E5: business operations associate; operations executive; operations analyst; process associate | F5: Excel; documentation; reporting; ownership; communication | G5: High | H5: Avoid roles that hide hard sales quotas under 'operations'.
A6: Procurement / Purchase Associate | B6: P1 | C6: Any graduation/BBA/B.Com depending on JD | D6: Purchase orders, supplier follow-up, invoice matching, requisitions, sourcing support | E6: procurement new associate; purchase associate; procurement operations; purchasing coordinator | F6: Excel; vendor management; P2P basics; accuracy | G6: High | H6: Prefer requisition/P2P support roles; avoid requiring engineering/category experience if not eligible.
A7: Supplier Onboarding / Vendor Management | B7: P1 | C7: BBA/any graduation; internships may count | D7: Vendor documentation, due diligence, portals, onboarding checklist, compliance, trackers | E7: supplier onboarding associate; vendor onboarding; vendor operations | F7: Excel; documentation; written communication; tracking | G7: High | H7: Confirm shift, work mode and client-facing requirements.
A8: Supply Chain Coordinator | B8: P1 | C8: BBA/SCM/logistics accepted in some roles | D8: Order tracking, inventory tracking, supplier communication, logistics coordination | E8: supply chain associate; SCM coordinator; logistics coordinator | F8: Excel; follow-up; data accuracy; coordination | G8: High | H8: Some roles request engineering/supply chain degree; confirm education.
A9: PMO Analyst / Project Coordinator | B9: P1 | C9: Any graduate for coordinator roles; PMO analyst may require Excel/reporting | D9: Project status, minutes, trackers, RAID logs, scheduling, stakeholder updates | E9: PMO analyst; project coordinator; project support associate | F9: Excel; PowerPoint; planning; communication | G9: High | H9: Do not target IT PMO roles that require technical project experience unless entry-level.
A10: HR Operations / People Operations | B10: P1 | C10: BBA/HR/any graduation depending on company | D10: Employee records, onboarding, HR ticketing, HR administration, data reports | E10: HR operations associate; people operations coordinator; HR apprentice | F10: Excel; discretion; organization; communication | G10: High | H10: Recruitment internships may be a stepping stone; check whether role is cold-calling candidates.
A11: Recruitment Coordination / TA Operations | B11: P2 | C11: BBA often accepted; coordinator experience useful | D11: Scheduling, applicant tracking, onboarding docs, candidate communication | E11: recruitment coordinator; talent operations; interview scheduler | F11: Calendar management; ATS familiarity; follow-up | G11: Medium | H11: Avoid commission-only recruiting or sales-style staffing jobs.
A12: Finance Operations / Procure-to-Pay | B12: P1 | C12: Any graduation/BBA/B.Com depending on posting | D12: Invoice processing, reconciliations, AP/AR support, vendor payment queues | E12: P2P new associate; accounts payable associate; finance operations associate | F12: Excel; numbers; accuracy; process controls | G12: High | H12: Some finance roles need accounting qualifications. Check rotation shifts.
A13: Risk / Compliance / KYC Operations | B13: P1/P2 | C13: BBA/commerce often accepted for junior ops; exact degree varies | D13: Document review, quality/risk checks, regulatory research, exception escalation | E13: quality and risk management associate; KYC analyst; compliance operations associate | F13: Research; attention to detail; written communication | G13: High | H13: KYC/AML roles may require specific experience; never claim certification you don't hold.
A14: Research / Due Diligence Associate | B14: P2 | C14: Any graduate in some firms; writing/research strength required | D14: Company research, regulatory databases, corporate registry searches, briefings | E14: business research associate; due diligence associate; analyst support | F14: Desk research; Excel; summarisation; source evaluation | G14: High | H14: Some roles need law/finance or language skills.
A15: Customer Operations (non-sales) | B15: P2 | C15: BBA/any graduate; fresher roles common | D15: Email/chat cases, order queries, issue resolution, customer records | E15: customer operations associate; customer support email chat; service delivery associate | F15: Written communication; troubleshooting; CRM; accuracy | G15: Medium | H15: Filter out business development, telesales, lead generation, cross-sell and upsell quotas.
... A43: International Business / Global Trade Support | B43: P2 | C43: BBA International Business is relevant when a role permits graduate entry | D43: Global orders, trade documentation, sourcing, cross-border coordination | E43: global business operations; trade support associate | F43: Documentation; communication; Excel; global awareness | G43: Medium | H43: Often niche; confirm required language and trade compliance experience.

Sheet Search Sources
A1: SEARCH PORTALS & RESEARCH SOURCES
A2: Run the scan across sources and maintain dates/result counts. Last initial scan date: 2026-10-11.
A4: Source / Portal | B4: Type | C4: URL / Starting Point | D4: Query & Filters to Use | E4: Validation Method | F4: Evidence Quality | G4: How to Use It | H4: Limitations / Warnings
A5: Official company portals | B5: Primary evidence | C5: Employer-specific official career portal | D5: Search role terms + Bengaluru/Bangalore + entry-level/graduate/0-2 years | E5: Always inspect the exact job page | F5: Highest | G5: Search before referral; capture official requisition ID | H5: https://www.google.com/search?q=official+company+careers+Bengaluru
A6: LinkedIn Jobs | B6: Public secondary source | C6: Jobs search | D6: Bengaluru + BBA fresher + role family; set date posted past week/month | E6: Open company job page; find company req ID in official portal | F6: High discovery, verify ID internally | G6: Do not treat LinkedIn job ID as internal requisition | H6: https://www.linkedin.com/jobs/
A7: Indeed India | B7: Public secondary source | C7: Jobs search | D7: Bengaluru business operations / procurement / HR ops / finance operations | E7: Distinguish direct employer listing from agency/redirect | F7: High discovery, verify freshness | G7: Indeed internal result tokens are not public job IDs | H7: https://in.indeed.com/
A8: Naukri | B8: Public secondary source | C8: Jobs search | D8: Bengaluru + fresher / 0-2 years + exact title; filter non-sales | E8: Prefer employer careers page for final status | F8: High discovery, verify ID | G8: Avoid job consultancy fee requests | H8: https://www.naukri.com/
A9: Foundit | B9: Public secondary source | C9: Jobs search | D9: Bangalore + early careers, shared services, operations, procurement | E9: Open full JD and capture post date | F9: High discovery, verify ID | G9: Check agency and employer name carefully | H9: https://www.foundit.in/
A10: Apna | B10: India job aggregator | C10: Jobs search | D10: Bangalore + fresher + operations/procurement/HR/purchase | E10: Fetch full job details and use public ID only as a public listing ID | F10: Medium-high discovery | G10: Does not guarantee an official requisition ID | H10: https://apna.co/
A11: Internshala Jobs | B11: Early career source | C11: Jobs search | D11: Bangalore + Operations, SCM, HR, Finance, General Management; experience 0 | E11: Record salary, applicants, posted age and embedded listing reference | F11: Medium-high discovery | G11: Verify startup/employer and exact scope, especially manager titles marked fresher | H11: https://internshala.com/jobs/
A12: Wellfound | B12: Startup jobs | C12: Startup hiring | D12: Bengaluru + operations/business/people/procurement; early career | E12: Verify current location and official apply destination | F12: Medium-high discovery | G12: Funding/company stage does not prove an active role | H12: https://wellfound.com/jobs
A13: Cutshort | B13: Startup/tech jobs | C13: Startup hiring | D13: Bangalore + operations/project coordinator/customer operations | E13: Use roles where business skills are central | F13: Medium discovery | G13: Confirm employer and whether tech degree is required | H13: https://cutshort.io/jobs
A14: Instahyre | B14: Startup/tech jobs | C14: Jobs search | D14: Bengaluru + business operations/customer success/people ops | E14: Filter experience; open employer portal | F14: Medium discovery | G14: Some listings skew technical or experienced | H14: https://www.instahyre.com/
A15: iimjobs | B15: Professional roles | C15: Jobs search | D15: Bengaluru + operations/PMO/marketing operations; filter fresher/early career | E15: Likely lower coverage for fresh BBA; use selectively | F15: Medium-low | G15: Many postings require MBA/experience | H15: https://www.iimjobs.com/
... A28: Startup funding / portfolio pages | B28: Startup universe research | C28: Startup intelligence | D28: Company newsrooms, investor portfolios, credible business press | E28: Funding is only a target-priority signal | F28: Secondary research | G28: Funding does not prove hiring | H28: https://www.ycombinator.com/

Sheet ATS Portal Map
A1: ATS & JOB-ID VERIFICATION MAP
A2: The same job may appear on several sites. Record the official requisition separately from the public platform ID.
A4: ATS / Portal | B4: Type | C4: Pattern / Link | D4: How to Extract ID and Verify | E4: Evidence Rule
A5: Workday | B5: ATS provider | C5: Company-specific Workday tenants such as company.wd5.myworkdayjobs.com | D5: Use exact company tenant + job title/location; save requisition code from full posting | E5: Official only if tenant is employer-confirmed
A6: SmartRecruiters | B6: ATS provider | C6: jobs.smartrecruiters.com/CompanyName/PostingID | D6: Posting ID often in URL; save title and exact company account | E6: Official if employer account is verified
A7: Greenhouse | B7: ATS provider | C7: boards.greenhouse.io/company/jobs/ID | D7: Job ID embedded in URL / posting page | E7: Official if company board is verified
A8: Lever | B8: ATS provider | C8: jobs.lever.co/company/ID | D8: UUID or job page identifier; record as ATS posting ID | E8: Official if company account verified
A9: SAP SuccessFactors | B9: ATS provider | C9: Company's official recruiting subdomain | D9: Search title + city; identifier may be requisition number, posting ID or application code | E9: Check employer domain
A10: Oracle / Taleo | B10: ATS provider | C10: Company-branded Oracle recruiting page | D10: Record requisition number from job detail, not search token | E10: Check employer domain
A11: iCIMS | B11: ATS provider | C11: jobs.company.com or careers-company.icims.com | D11: Record req ID in exact posting | E11: Check employer domain
A12: Workable | B12: ATS provider | C12: apply.workable.com/company | D12: Record unique posting link and any role ID shown | E12: Check employer domain
A13: LinkedIn Jobs | B13: Public job board | C13: linkedin.com/jobs/view/TITLE-ID | D13: LinkedIn ID is a public listing ID, not necessarily internal req ID | E13: Request company internal ID from employee
A14: Naukri / Indeed / Apna / Internshala | B14: Public job boards | C14: Platform-specific result pages | D14: Keep public listing ID separate; prefer direct official link for referral | E14: Search-board evidence only if no official page found

Sheet Application Tracker
A1: APPLICATION & REFERRAL TRACKER
A2: Start one row per application. Dropdowns keep statuses consistent; enter real dates and do not mark a referral complete until the employee confirms.
A4: Track ID | B4: Date Added | C4: Company | D4: Role | E4: Official Req ID | F4: Apply URL | G4: Resume Version | H4: Applied? | I4: Application Date | J4: Referral Contact | K4: LinkedIn URL | L4: Referral Asked? | M4: Referral Date | N4: Reply / Referral Status | O4: Last Follow-up | P4: Next Follow-up | Q4: Interview Stage | R4: Next Action | S4: Notes
A5: APP-001 | G5: BBA-IB CV v1 | H5: Not Started | L5: Not Contacted
A6: APP-002 | G6: BBA-IB CV v1 | H6: Not Started | L6: Not Contacted
A7: APP-003 | G7: BBA-IB CV v1 | H7: Not Started | L7: Not Contacted
A8: APP-004 | G8: BBA-IB CV v1 | H8: Not Started | L8: Not Contacted
A9: APP-005 | G9: BBA-IB CV v1 | H9: Not Started | L9: Not Contacted
A10: APP-006 | G10: BBA-IB CV v1 | H10: Not Started | L10: Not Contacted
A11: APP-007 | G11: BBA-IB CV v1 | H11: Not Started | L11: Not Contacted
A12: APP-008 | G12: BBA-IB CV v1 | H12: Not Started | L12: Not Contacted
A13: APP-009 | G13: BBA-IB CV v1 | H13: Not Started | L13: Not Contacted
A14: APP-010 | G14: BBA-IB CV v1 | H14: Not Started | L14: Not Contacted
A15: APP-011 | G15: BBA-IB CV v1 | H15: Not Started | L15: Not Contacted
A16: APP-012 | G16: BBA-IB CV v1 | H16: Not Started | L16: Not Contacted
... A54: APP-050 | G54: BBA-IB CV v1 | H54: Not Started | L54: Not Contacted

Sheet Referral Messages
A1: LINKEDIN REFERRAL MESSAGE LIBRARY
A2: Use official requisition IDs where available. When only an aggregator ID exists, say so clearly and ask the employee to locate the internal requisition.
A4: Message Type | B4: Best Use | C4: Copy-ready Draft
A5: Message Type | B5: Best use | C5: Copy-ready draft
A6: Referral request - official req ID | B6: Use when an internal requisition ID is verified | C6: Hi [Name], I’m a BBA graduate specialising in International Business and I’m looking for an entry-level role in Bengaluru in business operations, procurement, supply chain or project coordination. I found this role: [Role Title], [Official Req ID]. Would you be comfortable checking whether it is open in your internal referral portal and referring me if my profile fits? I have practical experience in event/campaign coordination, team supervision and business operations, and I’m happy to send my CV. Thank you for your time.
A7: Referral request - only public listing ID | B7: Use for Apna/LinkedIn/Indeed/Internshala listing without internal req | C7: Hi [Name], I found this public listing for [Role Title] at [Company]: [URL]. The public listing reference is [Public ID], which may not be the internal requisition ID. Could you please check whether the same role is open in your company’s referral portal and share the internal req ID if available? I’m a BBA International Business graduate and am targeting non-sales operations/procurement/coordinator roles in Bengaluru. I can share my CV. Thank you!
A8: Recruiter first message | B8: Send to a recruiter/hiring contact from a public professional profile | C8: Hello [Name], I’m a BBA graduate specialising in International Business and am exploring entry-level roles in Bengaluru in operations, procurement, supply chain, HR operations or project coordination. My practical experience includes event/campaign execution, team supervision and stakeholder coordination. I’m interested in [role/company] and can share my CV if there is a suitable opening. Thank you for your time.
A9: After applying | B9: Use after an online application or employee referral | C9: Hi [Name], thank you for referring/helping me with [Role Title, Req ID]. I’ve submitted my application on [date]. I’ll keep you updated if I receive an assessment or interview invitation. I appreciate your support.
A10: Follow-up after 5-7 days | B10: One polite follow-up, then pause | C10: Hi [Name], I wanted to politely follow up on [Role Title, Req ID] and check whether the opening is still active or whether any additional information is needed from me. No worries if the team has already progressed. Thank you again for your help.
A11: Recruiter application email / LinkedIn note | B11: When applying directly and a message field is available | C11: Hello Hiring Team, I am applying for [Role Title, Req ID] in Bengaluru. I hold a BBA in International Business and bring practical experience in event operations, campaign coordination, team supervision and stakeholder communication. I am interested in building my corporate career in [specific job family] and am comfortable learning new systems and operating procedures. My resume is attached for consideration. Thank you.

Sheet Master Prompt
A1: MASTER RESEARCH PROMPT & PROMPT PACK
A2: Copy the full main prompt from PROMPT-01 into a browsing-capable AI. Use the smaller prompts for daily batches or audits. A large prompt cannot force access to private ATS data; the agent must work within available tools.
A4: Prompt ID | B4: Prompt / Workflow | C4: Full Copyable Prompt
A5: PROMPT-01 | B5: Prompt 1 - Master all-in-one | C5: MASTER PROMPT: BENGALURU BBA FRESHER JOB INTELLIGENCE, COMPANY UNIVERSE & REFERRAL DATABASE Version 1.0 | Research date anchor: 11 October 2026 | Candidate: BBA, International Business | Target market: Bengaluru / Bangalore, India ROLE AND MISSION Act as a rigorous recruitment-market researcher, company-intelligence analyst, job-board auditor, ATS researcher, and career operations manager. Build and continuously maintain the broadest practical, source-backed database of real employers and current job opportunities for a BBA / BBA International Business graduate seeking entry-level work in Bengaluru. Do not merely generate company names. Search, verify, deduplicate, classify, score, cite, and structure results so the candidate can apply directly, ask LinkedIn connections for referrals, and track every action. CANDIDATE PROFILE AND CONSTRAINTS - Degree: BBA, specialization in International Business; Bengaluru, Karnataka. - Early-career / fresher for formal corporate experience. Relevant practical exposure includes event operations, coordination of brand campaigns/events, team supervision, stakeholder coordination, family-business exposure, digital-marketing learning/certificates, and business/customer-facing work. Do not inflate dates, titles, metrics, qualifications, or formal employment. - Core preference: non-sales corporate roles and an immediate job search. Prioritise business operations, procurement/purchasing, supplier onboarding, supply chain coordination, order management, finance operations / P2P / AP / AR support, project coordination / PMO support, HR operations, resource management, people services, risk/compliance operations where a BBA is accepted, business/research support, marketing operations, campaign coordination, customer operations (prefer email/chat/non-quota), e-commerce operations, logistics operations, and graduate/apprentice programmes. - Exclude from the primary list: field sales, business development, telecalling, cold calling, lead-generation quotas, commission-first jobs, insurance selling, hard cross-sell/up-sell, unpaid internships, roles demanding 2+ years when fresher is required, engineering-only roles, MBA-only programmes, and campus-restricted programmes for which the candidate's university is ineligible. Keep any backup voice-process or sales-adjacent listing on a separate clearly marked backup sheet only. - Candidate is open to full-time and paid internships/apprenticeships only where practical; identify night/rotational shifts, work-from-office, travel, stipends, probation, training bonds, fixed vs variable pay, and conversion caveats. NON-NEGOTIABLE TRUTH RULES 1. Never invent a company, opening, hiring claim, job ID, salary, posting date, degree requirement, deadline, location, recruiter name, email, referral contact, or apply URL. 2. Separate an official requisition ID / ATS ID from a LinkedIn job ID, Naukri listing ID, Apna public ID, Indeed redirect/internal search token, Internshala URL slug, or other aggregator ID. Label the ID type explicitly. If a public listing has no company requisition ID, use “Not exposed by source” and explain where the recruiter/employee should search. 3. Distinguish these states: (A) active on official employer portal and verified, (B) official page indexed but application status must be re-opened, (C) recent third-party listing only, (D) older listing needing confirmation, (E) talent network / programme page only, (F) closed/expired, (G) company target only with no vacancy yet verified. Never call C–G a confirmed live job. 4. Capture the actual date posted or exact relative age shown. Separately record the date/time checked and the date last verified. Do not treat search-engine crawl date as the original posting date. When the source gives only “last week,” retain that wording and, if estimating a calendar date, mark it “approximate, inferred.” 5. Every job row must have at least one source URL. Prefer the exact official job page, then the official ATS posting, then the exact public listing. Also capture an official company careers URL and a second corroborating source when available. 6. Do not assume every company named in a global Fortune list has a Bengaluru office or a current opening. Maintain a “company target universe” separately from the “live job database.” Use “Bengaluru presence unverified” when necessary. 7. Never claim the database is literally every Bengaluru employer or every job. State scope, source coverage, last scan date, and gaps. Continue researching the long tail systematically and keep an “unscanned / needs verification” queue. 8. Salaries must be transcribed exactly with currency and period. Do not convert annual to monthly without marking the calculation. When missing, write “Not disclosed.” Never fabricate HR contact details. Do not collect guessed personal emails. 9. Protect against scams: no candidate should pay recruitment fees, security deposits, interview fees, equipment fees, or training fees. Flag suspicious listings, mismatched titles, unrealistic salary, hidden sales targets, requests for money, WhatsApp-only recruiters, and unclear legal employer names. 10. Use company/role facts in the public domain only. Do not use private contact details or infer employee personal information. GEOGRAPHIC COVERAGE Cover Bengaluru and its employment clusters: Outer Ring Road, Bellandur, Marathahalli, Kadubeesanahalli, Whitefield, ITPL, Brookfield, Mahadevapura, Manyata Tech Park / Hebbal, Electronic City, Bommasandra, Peenya, Yeshwanthpur, Devanahalli, Koramangala, Indiranagar, MG Road/CBD, Jayanagar, JP Nagar, BTM, HSR Layout, Sarjapur Road, Bannerghatta Road, and nearby industrial areas. A role may be considered if officially listed in Bengaluru/Bangalore or clearly Bengaluru hybrid/remote eligible. Do not silently change a role's location. Keep nearby Karnataka roles on a separate optional tab. COMPANY UNIVERSE TO INVESTIGATE Build multiple overlapping but deduplicated lists: - U.S. Fortune 500 / Fortune 1000, Fortune Global 500, large multinational subsidiaries, and multinational Global Capability Centres (GCCs). Verify the annual list and rank from the relevant current Fortune source if recording a rank; otherwise label “Fortune status/rank to verify.” - Major Indian listed groups and large employers, including companies on BSE/NSE indices, conglomerates, banks, public-sector enterprises, consumer/FMCG, consulting, IT services, industrials, healthcare, telecom, logistics, retail, hospitality, travel, media and education. - Bengaluru-started or Bengaluru-operating startups, VC-backed companies, unicorns/scaleups, SaaS, fintech, e-commerce, logistics, healthtech, edtech, climate/EV, consumer brands, and emerging firms. Confirm current office/hiring location rather than assuming it. - Mid-market firms, BPO/shared services, staffing firms, professional services firms, hotels, hospitals, universities, research entities, nonprofits and business service providers that offer BBA-suitable work. - Employers whose jobs are hosted on Workday, SmartRecruiters, Greenhouse, Lever, iCIMS, SAP SuccessFactors, Oracle/Taleo, Workable or company-specific applicant-tracking systems. - Maintain “company target only” entries where no current role has been found. This is useful for follow-up, but it is not an open job. ROLE COVERAGE Run separate searches for at least these families, each with title variants: 1. Business Operations: Business Operations Associate, Operations Executive, Operations Associate, Business Process Associate, Operations Analyst, Process Associate, business support. 2. Procurement / Purchasing: Procurement New Associate, Procurement Operations, Purchase Associate, Purchasing Coordinator, Sourcing Support, Vendor Management, Supplier Onboarding, Purchase-to-Pay, Procure-to-Pay, invoice processing, accounts payable operations. 3. Supply Chain / Logistics: Supply Chain Associate, SCM Coordinator, order management, inventory coordinator, reverse logistics, logistics operations, fulfilment, delivery exception management, trade support, export-import documentation. 4. Project / Programme: PMO Analyst, Project Coordinator, Programme Associate, Project Support Associate, Delivery Coordinator, implementation coordinator. 5. Finance / Banking Operations: Finance Operations Associate, Transaction Processing, AP/AR Associate, Reconciliation, Payments Operations, Fund Operations, Asset Servicing, Client Onboarding, KYC/AML Operations, Trade Support, Corporate Actions, loan operations. Only include degree-eligible junior roles. 6. Risk / Compliance / Quality: Risk Operations Associate, Quality and Risk Management, compliance support, due-diligence research, process quality, controls/testing support, regulatory research. 7. HR / People Operations: HR Operations Associate, People Services Associate, HR Apprentice, Onboarding Coordinator, Resource Management Associate, Learning & Development Coordinator, Talent Operations, Recruitment Coordinator. Filter out commission-first recruitment and cold calling. 8. Research / Business Analysis: Research Associate, Business Research, Market Research, Due Diligence Associate, Junior Business Analyst, Reporting Analyst, MIS Executive, Sales Operations support only if it is non-quota. 9. Marketing / Brand / Communications: Marketing Operations, Campaign Coordinator, Brand Operations Associate, Digital Marketing, SEO, Content Marketing, PR, Events, Employer Branding, Customer/Community Programme Operations. Keep field sales/promoter work separate. 10. Customer / Service Operations: Email/Chat Support, Customer Operations, Service Delivery, Client Operations, Customer Success Operations without sales quota, ticket management and onboarding. Separately label voice processes and night shifts. 11. E-commerce / Retail / Hospitality: Marketplace Operations, Category Operations, Merchandising, Catalog Operations, Vendor Operations, Purchasing, Inventory, Hotel Procurement, Guest Operations, Travel Operations. 12. Startup / Founder’s Office: Founder’s Office Associate, Strategy & Operations Associate, Business Associate, Executive Assistant/Team Coordinator, Program Ops. Inspect scope, pay, hours and direct-sales burden. 13. Apprenticeships / Graduate Trainee / Internships: NATS/NAPS, company graduate programmes, paid internships with stated duration, stipend and conversion conditions. MANDATORY SOURCES AND SEARCH METHOD Search in batches and log which sources were searched and when: A. Official company career portals for target employers; filter location to Bengaluru/Bangalore, early career, internship, entry-level, graduate, analyst, associate, new associate, trainee and 0-2 years. B. The official ATS links found from company postings: Workday, Greenhouse, Lever, SmartRecruiters, iCIMS, SAP SuccessFactors, Oracle/Taleo and Workable. Search domain-restricted queries for role + employer + Bengaluru + “posted” / “requisition ID”. C. LinkedIn Jobs, Indeed India, Naukri, Foundit, Apna, Internshala, Wellfound, Cutshort, Instahyre, iimjobs, Shine, Freshersworld, TimesJobs, Hirist (only if business roles relevant), JobHai/WorkIndia when appropriate, National Career Service, AICTE internship portal, NATS/NAPS official channels and employer talent networks. D. Startup intelligence: Wellfound, YC Work at a Startup, company funding announcements, company newsrooms, credible business press, investor portfolio pages and startup career pages. Funding is a prioritisation signal, not proof of vacancy. E. Search-engine discovery as a backstop: targeted queries like `site:careers.company.com Bengaluru "associate"`, `site:myworkdayjobs.com Bengaluru "operations"`, `site:jobs.smartrecruiters.com Bengaluru procurement`, and variants for each role family. Open the job page itself; do not rely on snippets alone. F. Search all synonyms and spellings: Bengaluru, Bangalore, Bengaluru Urban, Whitefield, Outer Ring Road, Electronic City, entry-level, fresher, 0-1 years, 0-2 years, graduate, associate, new associate, analyst, coordinator, trainee, apprentice, intern. G. Search across the entire employer universe in a repeatable sequence: P1 employers first, then sector batches, then long-tail companies, with a queue so no sector or company batch is silently skipped. REQUIRED DATABASE TABS 1. Dashboard: date last refreshed, number of verified official openings, third-party-only leads, expired/needs-check leads, company targets, employer count by sector, jobs by role family, P1 apply queue, referral requests sent, applications submitted, interviews, offers. Use formulas linked to sheets. 2. Live Job Leads: one row per unique job/requisition. Required fields: Record ID; status; priority; company legal/employer name; brand/division; role title; job family; employment type; city/locality; work mode; shift; salary (exact source text); fixed/variable distinction; currency/pay period; posted date and source wording; date checked; closing date (only if source states); official requisition ID; public board listing ID; ID type; eligibility/degree; graduation year; years of experience; key responsibilities; exact required skills; preferred skills; salary; benefits; application link; official career portal link; source link 1; source link 2; official or third-party verification status; fresher eligibility evidence; BBA match score and reason; red flags; next action; date to recheck; referral status; application status. 3. Company Universe: one row per unique company/legal employer. Fields: company name; parent/brand; sector; subsector; employer type; Bengaluru-office evidence/status; Fortune/large-company status and source/year if verified; startup/funding signal and date if verified; estimated company size only if sourced; likely BBA-friendly role families; typical entry titles; official company website; official career portal; location-specific job search link; ATS platform if verified; LinkedIn Jobs link; company careers search link; source URL; last portal check; vacancy found? yes/no/unknown; notes; next check date. Do not fabricate size, funding, Fortune rank or Bangalore presence. 4. Role Taxonomy: role family, title variants, responsibilities, BBA suitability, commonly requested tools/skills, keywords to search, skills to develop, warning signs, target sectors, fit score. 5. Search Sources: source/site, type, exact URL, search query string, filters to set, source coverage, date last searched, result count, next check date, limitations. 6. ATS / Portal Map: employer, ATS platform, portal URL, method for location and fresher filtering, how to identify official requisition IDs. 7. Referral Tracker: company, employee name only if provided by candidate or public professional profile, relationship, LinkedIn profile URL if provided, target requisition ID, request date, response, referral confirmation, follow-up date, notes. Never guess contact details. 8. Application Tracker: application ID, company, role, official req ID, date applied, resume version, cover letter, referrer, status, next step, next follow-up, interview dates, offer details and notes. 9. Target Skills & CV Actions: only skills repeatedly required in verified target roles. Priority, job evidence, current evidence, gap, learning resource, 7/14/30-day actions. 10. Master Prompt and Prompt Pack: the master instruction and smaller prompts for daily scan, official-portal deep scan, startup scan, job-verification/dedup, referral batch creation, role-fit evaluation and weekly progress audit. 11. Source Log / Change Log: each source URL, date checked, what changed, before/after status, evidence and researcher note. REQUIRED ROW STANDARD FOR EVERY LIVE JOB - Job ID: exact spelling/case, and label whether it is an official ATS requisition, LinkedIn ID or external listing ID. - Posted: exact source display. If missing, say “Not exposed by source.” Never infer from crawl date. - Last verified: ISO date YYYY-MM-DD, local India time if time is available. - Salary: exact source wording or “Not disclosed.” - Fit score out of 100 with a brief evidence-based reason; do not treat it as a probability of getting hired. - Eligibility: state required degree and experience from the JD. If unknown, write “Needs full JD check.” - Link: exact application page, not only company homepage, where possible. - Status: Official-open / Official-listed-check-status / Third-party-only / Older-recheck / Programme-only / Closed / Target-only. - Source notes: short paraphrase and URL. - Referral readiness: “Ready” only when the role, current status, location, BBA eligibility, ID and apply link have been rechecked. Otherwise “Do not send yet”. - Duplicates: deduplicate same official requisition appearing on multiple sites; retain alternate listing URLs in source columns instead of creating duplicate jobs. PRIORITISATION SCORING (100 POINTS) - BBA and fresher eligibility: 25 - Non-sales alignment: 20 - Verified current/open status: 15 - Bengaluru location / reachable hybrid arrangement: 10 - Role skill fit from evidence: 10 - Company/career growth potential: 10 - Clear salary / stable employment / quality of terms: 5 - Referralability (known employee contact or clear official ID): 5 Apply 80-100 = P1, 65-79 = P2, 50-64 = P3, below 50 = do not prioritise. Lack of salary is not automatically disqualifying, but lower data confidence. An unknown requirement should not be silently scored as satisfied. DELIVERABLES Produce: A. A real Excel workbook with readable frozen headers, filters, proper widths, tables, validation dropdowns, conditional formatting, formula-backed dashboard, hyperlinks, date stamps and source URLs. Maintain separate live-job, company-universe, and application/referral tracking datasets. B. A downloadable plain-text master prompt and the same prompt inside the workbook. C. A concise run summary with counts by source, employer sector, role family and evidence status; list the most urgent verified P1 roles with exact ID and date. D. A list of source gaps and next search batches so “all companies” is pursued systematically, not falsely declared complete. E. For each selected role, generate a short, accurate referral message that names the employer, role title and official requisition ID. If the public listing has no internal requisition ID, ask the employee to find the matching opening internally. F. Keep an audit trail and last-checked date. Do not treat an old workbook as current without re-opening the links. EXECUTION PLAN: DO NOT SKIP STEPS Step 1: Establish current date/time in the user's locale. Record exact timestamp and timezone. Step 2: Refresh priority roles and job pages from official sources; search role families separately. Step 3: Search the company universe by sectors and ATS provider; record which company/portal batches have actually been checked. Step 4: Search current job boards as independent secondary sources; never rely on a single site. Step 5: Open official pages for candidates. Extract job ID, posted date, experience, degree, salary, role responsibilities, location, shift, work mode and close date. Capture evidence URLs. Step 6: Check duplicate IDs, duplicate titles with different req numbers, stale postings, conflicting qualifications, misleading title/description combinations, and uncertain BBA eligibility. Step 7: Add new rows to Live Job Leads only after exact role identity and source URL are captured. Add company-only rows separately. Step 8: Rank by fit and current-verification status; make the P1 list easy to action immediately. Step 9: Create referral messages and application plan based on exact requisition IDs. Step 10: Re-open top links, test that URLs lead to the intended page, confirm IDs, and update last-checked timestamps. Step 11: Export the workbook and master prompt; verify formulas, filter tables, links, and sheet counts. Step 12: Report what was checked, what was not, and any limitations honestly. START NOW First search and verify roles posted in the last 7 days, then last 30 days. Prioritise Bengaluru P1 non-sales jobs for a BBA fresher. Expand sectors and companies in a documented repeatable sequence, not by random sampling. Build the broad company universe in parallel but never confuse targets with vacancies. Return exact evidence. Keep working in batches until tool/time/source limits are reached; preserve a “next batch” queue for the next run.
A6: PROMPT-02 | B6: Prompt 2 - Daily current opening scan | C6: Search current Bengaluru/Bangalore vacancies for a BBA / BBA International Business fresher, prioritising non-sales corporate roles: business operations, procurement/purchase, supplier onboarding, supply chain, finance/P2P/AP operations, HR operations, resource management, PMO/project coordination, risk/compliance support, research, e-commerce/logistics operations and marketing operations. Search official company career portals and ATS pages first, then LinkedIn Jobs, Indeed, Naukri, Foundit, Apna, Internshala, Wellfound and Cutshort. Prioritise openings posted in the last 7 days, then last 30 days. For each job capture exact job title, legal employer, location, posted date wording, salary, employment type, required degree, experience, work mode/shift, official requisition ID, separate public listing ID, source URL, official apply URL, current status, evidence of fresher/BBA eligibility, fit score and next action. Do not invent IDs or mark a third-party page as official. Keep sales/BD/telecalling/commission-based jobs out of the primary list. Export new rows to the workbook and deduplicate on official requisition ID.
A7: PROMPT-03 | B7: Prompt 3 - Official ATS / career portal audit | C7: Take the existing company universe and inspect companies in batches of 25. For every employer, open the official career portal, search Bengaluru/Bangalore, and test relevant title variants for BBA freshers: associate, new associate, operations, procurement, purchasing, supplier onboarding, finance operations, HR operations, resource management, project coordinator, PMO, risk operations, research, marketing operations, and graduate/apprentice. Record date checked, ATS provider if observable, search filters, relevant role results, exact requisition ID, post date, eligibility and link. If no matching opening is found, mark “checked - no matching role found on this scan” with the search URL; do not leave it unclear whether it was checked. Keep company targets separate from live jobs.
A8: PROMPT-04 | B8: Prompt 4 - Startup / scaleup hiring sweep | C8: Run a Bengaluru startup and scaleup hiring scan for BBA fresher roles. Search official startup careers pages, Wellfound, Y Combinator Work at a Startup, Cutshort, LinkedIn, company newsroom/funding pages, and credible startup press/investor portfolio pages. Prioritise startups with a verified Bengaluru team or explicitly Bengaluru job location; mark other companies as location unverified. Roles: business operations, founder's office (fresher-friendly only), program associate, marketplace operations, purchasing, logistics, vendor onboarding, customer operations without sales quotas, HR/people ops, marketing/campaign ops, research and project coordination. Capture job IDs, post dates, salary, source links and fresher/degree eligibility. Funding announcements are a target-priority signal only, not evidence of a job vacancy. Flag unclear employer identity, unrealistic salary or sales duties hidden under an operations title.
A9: PROMPT-05 | B9: Prompt 5 - Data quality, ID verification and dedup | C9: Audit the job database row by row. For every listing, open the exact URL and check: current status; exact title; legal employer; Bengaluru location; requisition ID; whether ID is company ATS ID, LinkedIn ID, job-board ID or internal search token; posting date versus crawl date; degree; experience; work mode; shift; salary; full-time/internship/apprenticeship type; and direct apply URL. Remove unsupported assumptions. Deduplicate only when the same official requisition appears across portals; keep alternate source links on that row. Keep separate rows if official requisition IDs differ. Mark stale or unverified records clearly. Change “live/verified” only when the official page itself confirms the role is currently available. Flag mismatched title/description, old dates, unexplained salary gaps and possible scams. Run a broken-link and blank-ID audit before export.
A10: PROMPT-06 | B10: Prompt 6 - Referral batch builder | C10: From the verified P1/P2 jobs, create a referral-ready list sorted by company and relevance. For each role provide company, exact title, official requisition ID, official URL, one-sentence fit evidence, degree/experience eligibility and a brief professional LinkedIn message. When only a third-party listing ID exists, explicitly say this is not the internal requisition ID and ask the employee to find the equivalent opening in the internal referral portal. Never fabricate employee names, email addresses, referrals or company-internal IDs. Track who was contacted, when, reply, referral status and follow-up date.
A11: PROMPT-07 | B11: Prompt 7 - Candidate-to-role fit audit | C11: Use the candidate's actual resume text and each official job description to score fit across education eligibility, experience, skills evidence, role family, work mode/shift, location and employment type. Do not treat event or family-business exposure as formal corporate employment. Give an evidence-based score out of 100, identify exact gaps and suggest honest resume bullet edits tailored to each role. If the degree, graduation year, skills, shift availability or experience requirement is unknown, ask/mark unknown rather than assume. Do not create claims not found in the CV. Return the top 10 roles to apply for today with exact IDs and links.
A12: PROMPT-08 | B12: Prompt 8 - Weekly database progress audit | C12: Audit the job-search workbook from the past 7 days. Count new official-verified openings, third-party-only leads, stale/closed leads, companies checked, companies not checked, applications, referral requests, responses, interviews and offers. Reopen high-priority links; update status and last-checked dates. Identify sectors/companies not yet searched, role families with low coverage, missing source links, unknown IDs, duplicate records and follow-ups due. Reorder the next week's company/portal scan based on potential fit and source coverage. Do not claim comprehensive coverage unless the scan log proves which employers and sources were checked.
A13: PROMPT-09 | B13: Prompt 9 - Job-board query matrix | C13: For each target portal, run these separate searches in Bengaluru/Bangalore: “BBA fresher operations”, “business operations associate”, “procurement new associate”, “purchase associate fresher”, “supplier onboarding”, “supply chain coordinator”, “finance operations associate”, “procure to pay”, “HR operations associate”, “resource management associate”, “PMO analyst fresher”, “project coordinator”, “quality risk management associate”, “business research associate”, “e-commerce operations”, “reverse logistics intern”, “marketing operations coordinator”, “digital marketing intern”, “graduate trainee”, and “apprentice”. Apply fresher/0-2 years filters where available. Filter out hard sales/BDE/telecalling unless placed on a separate backup tab. Save the exact query URL and date searched for every portal and record result counts.
A14: PROMPT-10 | B14: Prompt 10 - Fortune / large-company universe audit | C14: Build and verify a list of Fortune US 500, Fortune Global 500, Fortune 1000 and large Indian listed companies with real Bengaluru operations or a plausible Bengaluru hiring channel. For every Fortune status, record which annual list is used, the publication year, exact name and rank only if directly sourced. Distinguish US Fortune 500 from Fortune Global 500. Verify whether each company has a Bengaluru office/site or a current Bengaluru job; never infer local presence just because the company is multinational. Add official website, official careers portal, ATS provider, job search link, typical BBA-friendly entry roles and scan status. Keep companies with unverified location in a separate section to investigate.

Sheet Source Log
A1: SOURCE LOG | EVIDENCE & AUDIT TRAIL
A2: These are sources consulted for the first seed batch. The next researcher should continue logging new portal scans and re-open every high-priority listing.
A4: Checked Date | B4: Company | C4: Role / Source | D4: Evidence Captured | E4: Evidence URL | F4: Confidence / Next Action
A5: 2026-10-11 | B5: Accenture | C5: Procure-to-Pay Operations New Associate | D5: Official requisition AIOC-S01664684; any graduation; 0-1 years; posted 8 days ago as indexed | E5: https://accenture.wd103.myworkdayjobs.com/accenturecareers/job/Bengaluru/Procure-to-Pay-Operations-New-Associate_AIOC-S01664684-1 | F5: Official source; status must be reopened before application
A6: 2026-10-11 | B6: Accenture | C6: Procurement Practice New Associate | D6: Official req AIOC-S01664045; any graduation; 0-1 years; posted 15 days ago as indexed | E6: https://accenture.wd103.myworkdayjobs.com/en-US/AccentureCareers/job/Bengaluru-BDC9A/Procurement-Practice-New-Associate_AIOC-S01664045-1 | F6: Official source; status must be reopened before referral
A7: 2026-10-11 | B7: EY | C7: Associate - Resource Management | D7: Req 1739823; published/date shown Oct 8, 2026 | E7: https://careers.ey.com/ey/job/Bengaluru-Associate-Resource-Management-KA-560048/1445690033/ | F7: Official source
A8: 2026-10-11 | B8: Allegis Global Solutions | C8: Onboarding Associate - APAC Shift - Supply Chain | D8: Official SmartRecruiters posting 744000152372369; indexed yesterday; hybrid/APAC shift | E8: https://jobs.smartrecruiters.com/AllegisGlobalSolutions/744000152372369-onboarding-associate-apac-shift-supply-chain-scm-bengaluru | F8: Official ATS source
A9: 2026-10-11 | B9: Allegis Global Solutions | C9: Onboarding Associate - Meta (Global) - Supply Chain | D9: Official SmartRecruiters posting 744000151812601; indexed today | E9: https://jobs.smartrecruiters.com/allegisglobalsolutions/744000151812601 | F9: Official ATS source
A10: 2026-10-11 | B10: JPMorgan Chase | C10: Business and Operations Specialist | D10: Apna listing 1129984729; fresher eligibility stated in public listing; internal req not exposed | E10: https://apna.co/job/bengaluru-bangalore/business-and-operations-specialist-1129984729 | F10: Third-party source; check official employer portal
A11: 2026-10-11 | B11: Marriott Hotels India | C11: Purchase Associate | D11: Apna listing 1912459795; fresher-only stated; internal req not exposed | E11: https://apna.co/job/bengaluru-bangalore/purchase-associate-1912459795 | F11: Third-party source; check official portal
A12: 2026-10-11 | B12: KPMG India Services | C12: Business Associate - Quality and Risk Management | D12: Apna listing 1779532141; fresher-can-apply stated; internal req not exposed | E12: https://apna.co/job/bengaluru-bangalore/business-associate-quality-and-risk-management-1779532141 | F12: Third-party source; check official portal
A13: 2026-10-11 | B13: Altisource | C13: Associate (Granite) | D13: Apna listing 1340046698; fresher-only label; specific eligibility unknown | E13: https://apna.co/job/bengaluru-bangalore/associate-1340046698 | F13: Third-party source; JD/eligibility requires check
A14: 2026-10-11 | B14: Pearson | C14: HR Operations Associate Intern | D14: Apna listing 1682511397; fresher-only label; internship duration shown inconsistently | E14: https://apna.co/job/bengaluru-bangalore/hr-operations-associate-intern-1682511397 | F14: Third-party source; verify stipend/duration
A15: 2026-10-11 | B15: Deutsche Bank | C15: Human Resources Apprentice 2026-2027 | D15: Apna listing 1125222884; 12-month apprenticeship, no permanent-job guarantee in description | E15: https://apna.co/job/bengaluru-bangalore/human-resources-apprentice-1125222884 | F15: Third-party source; verify current programme eligibility
... A23: 2026-10-11 | B23: Brickwork India | C23: Digital Marketing Intern | D23: Indeed page result dated 2026-10-10; direct listing ID unresolved; paid 3-month internship and night shift described | E23: https://in.indeed.com/q-bba-fresher-marketing-l-bengaluru%2C-karnataka-jobs.html | F23: Search-page evidence only; locate exact listing before applying

Sheet How To Use
A1: HOW TO USE THIS DATABASE
A2: This is a research OS for your job search: jobs, target companies, role taxonomy, portals, referrals and follow-ups are separated so the dataset stays honest and usable.
A4: Step | B4: Action | C4: Output / Definition of Done | D4: Suggested cadence
A5: 1 | B5: Start with Dashboard and read evidence labels | C5: Know the difference between verified official role, third-party lead and company target. | D5: Every session
A6: 2 | B6: Apply to P1 roles in Live Jobs | C6: Each application has exact role title, official/public ID type and apply URL recorded. | D6: Daily
A7: 3 | B7: Send referral request using Referral Messages | C7: Use official req ID where known; for public IDs ask the employee to locate internal req. | D7: Daily
A8: 4 | B8: Open Company Universe in priority order | C8: Search the official career portal using the role families from Role Taxonomy; update portal status and date checked. | D8: 25 companies per session
A9: 5 | B9: Run Master Prompt PROMPT-01 | C9: Use a browsing-capable AI with access to web and file export; research official and third-party sources. | D9: Daily or every 2 days
A10: 6 | B10: Run prompts 2-5 in separate batches | C10: Daily sweep, official ATS audit, startup sweep and ID/dedup quality audit. | D10: As needed
A11: 7 | B11: Update Application Tracker | C11: Update status, referrer, dates, interviews and next action. | D11: After every action
A12: 8 | B12: Recheck age of listings | C12: Reopen anything older than 7 days before referral; anything older than 30 days is stale unless official page confirms still open. | D12: Daily
A13: 9 | B13: Expand company coverage | C13: Filter Company Universe by sector and process in a documented sequence; don't randomly skip batches. | D13: Weekly
A14: 10 | B14: Do quality control | C14: No made-up IDs, salary, posting dates, HR details or vacancy status. Keep company targets separate from live roles. | D14: Every export
A15: 11 | B15: Protect yourself from fraud | C15: Never pay to apply or secure an interview; verify legal employer, domains and offer details. | D15: Always
... A22: Application Tracker v2 | B22: Application, referral, follow-up and interview status | C22: Update statuses immediately after every action | D22: Public job-board IDs are not internal requisition IDs

Sheet Company Research Links
A1: COMPANY INTELLIGENCE | RESEARCH LINK DIRECTORY
A2: 500+ company-specific discovery shortcuts for verifying websites, career portals, Bengaluru presence, Fortune status, company size and public evidence. Search links are not themselves verification.
A4: Company ID | B4: Company Name | C4: Sector | D4: Employer Type | E4: Official Website Discovery Search | F4: Careers Portal Discovery Search | G4: LinkedIn Company Search | H4: Bengaluru Office Evidence Search | I4: Fortune / Annual Ranking Evidence Search | J4: Company Size / Revenue Evidence Search | K4: Verification Rule
A5: CO-0001 | B5: Accenture | C5: IT Services, Consulting & BPO | D5: MNC / professional services | E5: https://www.google.com/search?q=Accenture+official+company+website+about+us | F5: https://www.google.com/search?q=Accenture+official+careers+Bengaluru+Bangalore | G5: https://www.linkedin.com/search/results/companies/?keywords=Accenture | H5: https://www.google.com/search?q=Accenture+Bengaluru+office+location+India | I5: https://www.google.com/search?q=Accenture+Fortune+500+Fortune+Global+500+Fortune+1000+2026+rank | J5: https://www.google.com/search?q=Accenture+revenue+employee+count+official+annual+report | K5: Not yet verified - use these links to collect evidence; do not infer local presence or ranking.
A6: CO-0002 | B6: Capgemini | C6: IT Services, Consulting & BPO | D6: MNC / professional services | E6: https://www.google.com/search?q=Capgemini+official+company+website+about+us | F6: https://www.google.com/search?q=Capgemini+official+careers+Bengaluru+Bangalore | G6: https://www.linkedin.com/search/results/companies/?keywords=Capgemini | H6: https://www.google.com/search?q=Capgemini+Bengaluru+office+location+India | I6: https://www.google.com/search?q=Capgemini+Fortune+500+Fortune+Global+500+Fortune+1000+2026+rank | J6: https://www.google.com/search?q=Capgemini+revenue+employee+count+official+annual+report | K6: Not yet verified - use these links to collect evidence; do not infer local presence or ranking.
A7: CO-0003 | B7: Tata Consultancy Services (TCS) | C7: IT Services, Consulting & BPO | D7: MNC / professional services | E7: https://www.google.com/search?q=Tata+Consultancy+Services+%28TCS%29+official+company+website+about+us | F7: https://www.google.com/search?q=Tata+Consultancy+Services+%28TCS%29+official+careers+Bengaluru+Bangalore | G7: https://www.linkedin.com/search/results/companies/?keywords=Tata+Consultancy+Services+%28TCS%29 | H7: https://www.google.com/search?q=Tata+Consultancy+Services+%28TCS%29+Bengaluru+office+location+India | I7: https://www.google.com/search?q=Tata+Consultancy+Services+%28TCS%29+Fortune+500+Fortune+Global+500+Fortune+1000+2026+rank | J7: https://www.google.com/search?q=Tata+Consultancy+Services+%28TCS%29+revenue+employee+count+official+annual+report | K7: Not yet verified - use these links to collect evidence; do not infer local presence or ranking.
A8: CO-0004 | B8: Infosys | C8: IT Services, Consulting & BPO | D8: MNC / professional services | E8: https://www.google.com/search?q=Infosys+official+company+website+about+us | F8: https://www.google.com/search?q=Infosys+official+careers+Bengaluru+Bangalore | G8: https://www.linkedin.com/search/results/companies/?keywords=Infosys | H8: https://www.google.com/search?q=Infosys+Bengaluru+office+location+India | I8: https://www.google.com/search?q=Infosys+Fortune+500+Fortune+Global+500+Fortune+1000+2026+rank | J8: https://www.google.com/search?q=Infosys+revenue+employee+count+official+annual+report | K8: Not yet verified - use these links to collect evidence; do not infer local presence or ranking.
A9: CO-0005 | B9: Wipro | C9: IT Services, Consulting & BPO | D9: MNC / professional services | E9: https://www.google.com/search?q=Wipro+official+company+website+about+us | F9: https://www.google.com/search?q=Wipro+official+careers+Bengaluru+Bangalore | G9: https://www.linkedin.com/search/results/companies/?keywords=Wipro | H9: https://www.google.com/search?q=Wipro+Bengaluru+office+location+India | I9: https://www.google.com/search?q=Wipro+Fortune+500+Fortune+Global+500+Fortune+1000+2026+rank | J9: https://www.google.com/search?q=Wipro+revenue+employee+count+official+annual+report | K9: Not yet verified - use these links to collect evidence; do not infer local presence or ranking.
A10: CO-0006 | B10: Cognizant | C10: IT Services, Consulting & BPO | D10: MNC / professional services | E10: https://www.google.com/search?q=Cognizant+official+company+website+about+us | F10: https://www.google.com/search?q=Cognizant+official+careers+Bengaluru+Bangalore | G10: https://www.linkedin.com/search/results/companies/?keywords=Cognizant | H10: https://www.google.com/search?q=Cognizant+Bengaluru+office+location+India | I10: https://www.google.com/search?q=Cognizant+Fortune+500+Fortune+Global+500+Fortune+1000+2026+rank | J10: https://www.google.com/search?q=Cognizant+revenue+employee+count+official+annual+report | K10: Not yet verified - use these links to collect evidence; do not infer local presence or ranking.
A11: CO-0007 | B11: HCLTech | C11: IT Services, Consulting & BPO | D11: MNC / professional services | E11: https://www.google.com/search?q=HCLTech+official+company+website+about+us | F11: https://www.google.com/search?q=HCLTech+official+careers+Bengaluru+Bangalore | G11: https://www.linkedin.com/search/results/companies/?keywords=HCLTech | H11: https://www.google.com/search?q=HCLTech+Bengaluru+office+location+India | I11: https://www.google.com/search?q=HCLTech+Fortune+500+Fortune+Global+500+Fortune+1000+2026+rank | J11: https://www.google.com/search?q=HCLTech+revenue+employee+count+official+annual+report | K11: Not yet verified - use these links to collect evidence; do not infer local presence or ranking.
A12: CO-0008 | B12: Tech Mahindra | C12: IT Services, Consulting & BPO | D12: MNC / professional services | E12: https://www.google.com/search?q=Tech+Mahindra+official+company+website+about+us | F12: https://www.google.com/search?q=Tech+Mahindra+official+careers+Bengaluru+Bangalore | G12: https://www.linkedin.com/search/results/companies/?keywords=Tech+Mahindra | H12: https://www.google.com/search?q=Tech+Mahindra+Bengaluru+office+location+India | I12: https://www.google.com/search?q=Tech+Mahindra+Fortune+500+Fortune+Global+500+Fortune+1000+2026+rank | J12: https://www.google.com/search?q=Tech+Mahindra+revenue+employee+count+official+annual+report | K12: Not yet verified - use these links to collect evidence; do not infer local presence or ranking.
A13: CO-0009 | B13: LTIMindtree | C13: IT Services, Consulting & BPO | D13: MNC / professional services | E13: https://www.google.com/search?q=LTIMindtree+official+company+website+about+us | F13: https://www.google.com/search?q=LTIMindtree+official+careers+Bengaluru+Bangalore | G13: https://www.linkedin.com/search/results/companies/?keywords=LTIMindtree | H13: https://www.google.com/search?q=LTIMindtree+Bengaluru+office+location+India | I13: https://www.google.com/search?q=LTIMindtree+Fortune+500+Fortune+Global+500+Fortune+1000+2026+rank | J13: https://www.google.com/search?q=LTIMindtree+revenue+employee+count+official+annual+report | K13: Not yet verified - use these links to collect evidence; do not infer local presence or ranking.
A14: CO-0010 | B14: Mphasis | C14: IT Services, Consulting & BPO | D14: MNC / professional services | E14: https://www.google.com/search?q=Mphasis+official+company+website+about+us | F14: https://www.google.com/search?q=Mphasis+official+careers+Bengaluru+Bangalore | G14: https://www.linkedin.com/search/results/companies/?keywords=Mphasis | H14: https://www.google.com/search?q=Mphasis+Bengaluru+office+location+India | I14: https://www.google.com/search?q=Mphasis+Fortune+500+Fortune+Global+500+Fortune+1000+2026+rank | J14: https://www.google.com/search?q=Mphasis+revenue+employee+count+official+annual+report | K14: Not yet verified - use these links to collect evidence; do not infer local presence or ranking.
A15: CO-0011 | B15: Genpact | C15: IT Services, Consulting & BPO | D15: MNC / professional services | E15: https://www.google.com/search?q=Genpact+official+company+website+about+us | F15: https://www.google.com/search?q=Genpact+official+careers+Bengaluru+Bangalore | G15: https://www.linkedin.com/search/results/companies/?keywords=Genpact | H15: https://www.google.com/search?q=Genpact+Bengaluru+office+location+India | I15: https://www.google.com/search?q=Genpact+Fortune+500+Fortune+Global+500+Fortune+1000+2026+rank | J15: https://www.google.com/search?q=Genpact+revenue+employee+count+official+annual+report | K15: Not yet verified - use these links to collect evidence; do not infer local presence or ranking.
... A510: CO-0506 | B510: SIDBI | C510: Public Sector, Infrastructure & Utilities | D510: Public sector / infrastructure | E510: https://www.google.com/search?q=SIDBI+official+company+website+about+us | F510: https://www.google.com/search?q=SIDBI+official+careers+Bengaluru+Bangalore | G510: https://www.linkedin.com/search/results/companies/?keywords=SIDBI | H510: https://www.google.com/search?q=SIDBI+Bengaluru+office+location+India | I510: https://www.google.com/search?q=SIDBI+Fortune+500+Fortune+Global+500+Fortune+1000+2026+rank | J510: https://www.google.com/search?q=SIDBI+revenue+employee+count+official+annual+report | K510: Not yet verified - use these links to collect evidence; do not infer local presence or ranking.

Sheet Verified Openings
A1: RECENTLY RESEARCHED BENGALURU LEADS | 43 CORE RECORDS + SEE VERIFIED ADDENDUM
A2: Snapshot 11 Oct 2026. All leads require a day-of-application status recheck. A job-board ID is not an internal requisition ID; benefits and salary fields explicitly mark missing data. A later official Accenture Supply Chain Operations role is recorded separately in Verified Addendum and Application Tracker v2.
A3: Scoring: 35% CV match + 25% eligibility + 15% freshness + 15% source reliability + 5% pay transparency + 5% benefits evidence. Priority scores rank research/actions, not callback probabilities. Click every link and re-confirm availability before referral.
A4: Record ID | B4: Rank | C4: Priority Tier | D4: Weighted Priority Score | E4: CV Match (0–100) | F4: Eligibility Fit (0–100) | G4: Freshness Evidence (0–100) | H4: Source Reliability (0–100) | I4: Pay Transparency (0–100) | J4: Benefits Evidence (0–100) | K4: Company | L4: Role Title | M4: Role Family | N4: Official Job / Requisition ID | O4: Public Job-Board ID | P4: ID Type / Interpretation | Q4: Opening Status / Evidence | R4: Posting Date / Age Evidence | S4: Last Checked | T4: Location | U4: Work Mode | V4: Employment Type | W4: Experience Requirement | X4: Education / Degree Requirement | Y4: Employer-Stated Salary / CTC | Z4: External Salary Benchmark (not an offer) | AA4: Bonus / Variable Pay / Stock Disclosure | AB4: Joining Bonus Disclosure | AC4: Medical / Health Insurance | AD4: Leave / Holidays | AE4: Transport / Travel / Meals | AF4: Shift / Weekend / Hours | AG4: Main Responsibilities / Role Detail | AH4: CV Match Evidence | AI4: Gaps / Risks / Questions to Verify | AJ4: Direct Apply / Job Listing Link | AK4: Official Employer / ATS Link | AL4: Secondary / Source Link | AM4: Source Confidence | AN4: Next Action | AO4: Application Status | AP4: Referral Status | AQ4: Follow-up Date | AR4: Interview Focus / Notes
A5: LIVE-035 | B5: 1 | C5: P1 – Apply first | D5: =ROUND(E5*0.35+F5*0.25+G5*0.15+H5*0.15+I5*0.05+J5*0.05,1) | E5: 96 | F5: 100 | G5: 95 | H5: 85 | I5: 100 | J5: 60 | K5: Nathaniel School of Music | L5: Operations & Admin Executive (Education) – Fresher | M5: Operations / admin / reporting / events | O5: 1791182216 | P5: Internshala listing reference/slug suffix; not internal requisition | Q5: C – detailed Internshala listing with application deadline and one opening | R5: Posted 6 days ago; apply by 4 Nov 2026; 44 applicants at detail retrieval | S5: 46306 | T5: Bengaluru | U5: On-site at music school/studio | V5: Full-time | W5: No experience required; starts immediately | X5: BBA, commerce and MBA graduates explicitly welcomed in description | Y5: ₹3,00,000–₹4,20,000/year listed; salary breakup not shown | Z5: Advertised annual salary range; verify if employer calls it CTC and what is fixed | AA5: No bonus/variable pay disclosed | AB5: No joining bonus disclosed | AC5: No health/insurance details disclosed | AD5: Leave not specified | AE5: Travel/cab/meal not disclosed | AF5: Company says six days/week; exact role hours not stated | AG5: Track attendance/billing/class schedules; coordinate teachers; keep student records accurate; manage learning portal issues; prepare weekly reports; support events and app testing. | AH5: Outstanding fit: BBA explicitly invited; Excel/Google Sheets and data accuracy requested; CV has event coordination, scheduling, admin, reports, and AI/web-app projects. | AI5: Six-day working week; one opening and moderate applicant volume. Ask daily hours, weekly off, insurance/PF, role priorities and growth path. | AJ5: https://internshala.com/job/detail/fresher-operations-admin-executive-education-job-in-bangalore-at-nathaniel-school-of-music1791182216/ | AK5: https://internshala.com/job/detail/fresher-operations-admin-executive-education-job-in-bangalore-at-nathaniel-school-of-music1791182216/ | AM5: Medium-high – detailed listing with deadline, pay, duties and BBA fit | AN5: Apply by 4 Nov 2026. Tailor CV to Excel, weekly reporting, schedules, student records, event logistics and app testing. | AO5: Not Started | AP5: Not Contacted
A6: LIVE-003 | B6: 2 | C6: P1 – Apply first | D6: =ROUND(E6*0.35+F6*0.25+G6*0.15+H6*0.15+I6*0.05+J6*0.05,1) | E6: 92 | F6: 97 | G6: 95 | H6: 100 | I6: 60 | J6: 55 | K6: Accenture | L6: Procurement Practice New Associate | M6: Procurement / procure-to-pay operations | N6: AIOC-S01667387 | P6: Official Accenture requisition ID | Q6: A – official Accenture listing indexed today and shows Apply for this job; re-open exact URL before applying | R6: Posting date not shown; official listing crawled 11 Oct 2026 | S6: 46306 | T6: Bengaluru | U6: On-site/remote not specified | V6: Full-time | W6: 0–1 years; page header says 0–2 years | X6: Any Graduation | Y6: Not disclosed by employer | Z6: ₹3–5 LPA Glassdoor estimate for a related Procurement Operations New Associate Bengaluru posting; estimate only, not an offer | AA6: Company benefit page describes bonus programs, but role-specific eligibility/payout is not disclosed | AB6: Not disclosed | AC6: Accenture India benefit page describes medical coverage; exact role/coverage terms not shown | AD6: Company page says state-based PTO including earned/sick/casual leave and 10 public holidays | AE6: Not disclosed for this opening | AF6: Rotational shifts may be required | AG6: Transactional procurement; supplier records/catalogue/user authorisations, invoice/PO matching, compliance checks, supplier communication, documentation and service levels. | AH6: Strong fit with inventory, supplier restocking, accuracy checks, Excel, records, data quality and coordination. | AI6: Job refers to ERP and procurement processes; no SAP/Ariba or AP/P2P experience stated on CV. Learn workflow terms before interview. | AJ6: https://www.accenture.com/in-en/careers/jobdetails?id=AIOC-S01667387_en | AK6: https://www.accenture.com/in-en/careers/jobdetails?id=AIOC-S01667387_en | AL6: https://www.glassdoor.co.in/job-listing/procurement-operations-new-associate-accenture-JV_IC2940587_KO0%2C36_KE37%2C46.htm?jl=1010225238230 | AM6: High – official role page and matching third-party salary estimate | AN6: Apply on official page; mention Excel/data verification and vendor coordination. Ask for CTC break-up, shift, medical coverage and variable pay. | AO6: Not Started | AP6: Not Contacted | AR6: Salary is a third-party estimate. No joining bonus is disclosed.
A7: LIVE-005 | B7: 3 | C7: P1 – Apply first | D7: =ROUND(E7*0.35+F7*0.25+G7*0.15+H7*0.15+I7*0.05+J7*0.05,1) | E7: 92 | F7: 96 | G7: 93 | H7: 100 | I7: 60 | J7: 55 | K7: Accenture | L7: Procurement Practice New Associate | M7: Procurement support | N7: AIOC-S01664045 | P7: Official Accenture requisition ID | Q7: A – official page crawled yesterday; recheck Apply state | R7: Posting date not shown; official listing crawled 10 Oct 2026 | S7: 46306 | T7: Bengaluru | U7: Not specified | V7: Full-time | W7: 0–1 years; page header says 0–2 years | X7: Any Graduation | Y7: Not disclosed by employer | Z7: ₹3–5 LPA estimated for a closely related Accenture procurement new-associate role (Glassdoor; not official CTC) | AA7: Role-specific bonus not stated; company-wide bonus policy exists | AB7: Not disclosed | AC7: Medical coverage is described company-wide; role specifics unknown | AD7: State-based PTO; 10 public holidays in company-wide policy | AE7: Not disclosed | AF7: Rotational shifts may be required | AG7: Procurement operations support, PO/vendor data, supplier documentation, compliance checks, SLA/accuracy, and stakeholder communication. | AH7: CV evidence: supplier restocking, inventory control, shipment receipt checks, data verification and Excel. | AI7: Ariba/SAP/platform knowledge may be expected in procurement roles; these tools are not listed in CV. Do not claim hands-on experience. | AJ7: https://www.accenture.com/in-en/careers/jobdetails?id=AIOC-S01664045_en | AK7: https://www.accenture.com/in-en/careers/jobdetails?id=AIOC-S01664045_en | AL7: https://www.glassdoor.co.in/job-listing/procurement-operations-new-associate-accenture-JV_IC2940587_KO0%2C36_KE37%2C46.htm?jl=1010225238230 | AM7: High – official role page; third-party estimate is adjacent role | AN7: Apply; tailor CV around vendor follow-up, inventory, record accuracy and AI workflow tools. | AO7: Not Started | AP7: Not Contacted
A8: LIVE-024 | B8: 4 | C8: P1 – Apply first | D8: =ROUND(E8*0.35+F8*0.25+G8*0.15+H8*0.15+I8*0.05+J8*0.05,1) | E8: 95 | F8: 100 | G8: 90 | H8: 85 | I8: 100 | J8: 20 | K8: SharePal | L8: Associate – Purchase – Fresher | M8: Purchasing / vendor operations | O8: 1790684619 | P8: Internshala listing reference/slug suffix; not an internal req ID | Q8: C – Internshala live listing with Apply flow; verify employer status before referral | R8: Posted 1 week ago; apply-by 29 Oct 2026; 252 applicants at detail retrieval | S8: 46306 | T8: Bengaluru | U8: Not stated; Bangalore-only candidates may apply | V8: Full-time | W8: No experience required; starts immediately | X8: Degree eligibility not further constrained in retrieved listing; Bangalore-only | Y8: ₹4,00,000–₹5,00,000/year listed; salary break-up not provided | Z8: Employer-advertised annual pay range; not independently verified as CTC | AA8: No variable/bonus detail disclosed | AB8: No joining bonus disclosed | AC8: No health/insurance detail listed | AD8: No leave/holiday detail listed | AE8: No transport/travel allowance listed | AF8: Workday/hours/weekly off not disclosed | AG8: Execute planned and just-in-time purchases; source and manage repair/service vendors; coordinate warehouse bin replenishment; negotiate cost/SLAs/quality; expedite repairs. | AH8: Very strong: supplier restocking and vendor communication in family retail, inventory control at Aero India, event vendor coordination, operations records. | AI8: No purchasing-software or negotiation metrics evidenced; use honest examples and show structured vendor follow-up. | AJ8: https://internshala.com/job/detail/fresher-associate-purchase-job-in-bangalore-at-sharepal1790684619/ | AK8: https://internshala.com/job/detail/fresher-associate-purchase-job-in-bangalore-at-sharepal1790684619/ | AM8: Medium-high – detailed internship-platform listing with salary and deadline | AN8: Apply before 29 Oct 2026; tailor CV for purchasing, vendor sourcing, stock replenishment and fast turnaround. | AO8: Not Started | AP8: Not Contacted
A9: LIVE-004 | B9: 5 | C9: P1 – Apply first | D9: =ROUND(E9*0.35+F9*0.25+G9*0.15+H9*0.15+I9*0.05+J9*0.05,1) | E9: 90 | F9: 96 | G9: 92 | H9: 100 | I9: 55 | J9: 55 | K9: Accenture | L9: Procure to Pay Operations New Associate – Master Data Management | M9: P2P / finance operations / master data | N9: AIOC-S01664695 | P9: Official Accenture requisition ID | Q9: A – official listing was available two days before snapshot; confirm Apply button | R9: Posting date not shown; official listing crawled 9 Oct 2026 | S9: 46306 | T9: Bengaluru | U9: Not specified; role may require rotational shifts | V9: Full-time | W9: 0–1 years; page header says 0–2 years | X9: Any Graduation | Y9: Not disclosed by employer | Z9: Public estimates vary: related Accenture procurement roles have been estimated around ₹3–5 LPA; employee-reported P2P New Associate data also shows lower ₹2–3 LPA samples. Not an employer offer. | AA9: Company-wide bonus programmes exist; job-specific target or amount not disclosed | AB9: Not disclosed | AC9: Company-wide medical coverage is described in Accenture India benefits page; role-specific cover to confirm | AD9: State-based PTO and 10 public holidays per company-wide page | AE9: Not disclosed | AF9: Rotational shifts may be required | AG9: Invoice/P2P transaction handling, PO/non-PO processing, expense/invoice validation, ERP posting, tax discrepancy support, master data consistency and SLA accuracy. | AH9: Spreadsheet accuracy, error logging and structured data checking are highly relevant to master-data quality and transaction validation. | AI9: No formal ERP/SAP/Ariba experience shown; be ready to explain attention-to-detail process and learn two/three-way matching. | AJ9: https://www.accenture.com/in-en/careers/jobdetails?id=AIOC-S01664695_en | AK9: https://www.accenture.com/in-en/careers/jobdetails?id=AIOC-S01664695_en | AL9: https://www.glassdoor.co.in/Salary/Accenture-Procure-to-Pay-Operations-New-Associate-Salaries-E4138_D_KO10%2C49.htm | AM9: High – official listing; salary estimates are noisy | AN9: Apply; prepare invoice/PO/GRN, master-data accuracy and discrepancy-resolution examples; verify salary and shift. | AO9: Not Started | AP9: Not Contacted
A10: LIVE-001 | B10: 6 | C10: P1 – Apply first | D10: =ROUND(E10*0.35+F10*0.25+G10*0.15+H10*0.15+I10*0.05+J10*0.05,1) | E10: 95 | F10: 96 | G10: 96 | H10: 100 | I10: 20 | J10: 35 | K10: Allegis Global Solutions | L10: Onboarding Associate – APAC Shift – Supply Chain / SCM | M10: Supplier onboarding / compliance operations | N10: 744000152077429 | O10: Apna 1087295269 | P10: Official SmartRecruiters ATS ID + separate Apna ID | Q10: A – official employer ATS posting found current today; page displays interest action; recheck before referral | R10: Not stated in posting; official ATS page crawled 11 Oct 2026 | S10: 46306 | T10: Bengaluru | U10: Hybrid (Mon–Wed per posting) | V10: Full-time | W10: Prior similar experience is an advantage; internships / academic projects / coordination experience considered | X10: Bachelor’s degree, related major, or equivalent business experience | Y10: Not disclosed on this role page | Z10: No reliable job-specific public estimate found | AA10: Not disclosed on this role page | AB10: Not disclosed | AC10: Not disclosed on target role page; confirm with recruiter | AD10: Not disclosed on target role page | AE10: Travel/cab/meal benefit not disclosed on target role page | AF10: APAC shift: 10:00 AM–7:00 PM; occasional flexibility may be required | AG10: Supplier vetting/onboarding, completeness checks, compliance documentation, follow-ups, SLA tracking, records, dashboards, audits and cross-team coordination. | AH10: Excellent transfer: Instawork data verification, error documentation, retail supplier restocking, incoming delivery receipt checks, event/vendor coordination and Excel. | AI10: No named supplier portal/VMS, formal compliance workflow, or SAP/Ariba evidence on CV; position as transferable coordination and data accuracy, not prior formal procurement experience. | AJ10: https://jobs.smartrecruiters.com/AllegisGlobalSolutions/744000152077429-supply-chain-onboarding-associate-apac | AK10: https://jobs.smartrecruiters.com/AllegisGlobalSolutions/744000152077429-supply-chain-onboarding-associate-apac | AL10: https://apna.co/job/bengaluru-bangalore/supply-chain-onboarding-associate-1087295269 | AM10: High – official ATS posting with detailed responsibilities and schedule | AN10: Apply on ATS; then ask AGS employees to refer using ATS ID 744000152077429. Confirm work mode, pay, and benefits. | AO10: Not Started | AP10: Not Contacted | AR10: Official posting describes accuracy, follow-up ownership and supplier-record maintenance; excellent CV match.
A11: LIVE-007 | B11: 7 | C11: P1 – Apply first | D11: =ROUND(E11*0.35+F11*0.25+G11*0.15+H11*0.15+I11*0.05+J11*0.05,1) | E11: 90 | F11: 95 | G11: 82 | H11: 100 | I11: 60 | J11: 55 | K11: Accenture | L11: Procurement Operations New Associate | M11: Procurement support / supplier management | N11: AIOC-S01660205 | P11: Official Accenture requisition ID | Q11: B – official listing recently indexed; re-open direct page to confirm availability | R11: Posting date not shown; official listing crawled within last week | S11: 46306 | T11: Bengaluru | U11: Shift/relocation flexibility may be required | V11: Full-time | W11: 0–1 years; page header says 0–2 years | X11: Any Graduation | Y11: Not disclosed by employer | Z11: ₹3–5 LPA estimate from a similar Accenture procurement new-associate posting; not an offer | AA11: Company-wide bonus programmes described; role eligibility unknown | AB11: Not disclosed | AC11: Company-wide medical cover described; exact plan to confirm | AD11: State-based PTO; 10 public holidays described on employer benefit page | AE11: No transport allowance confirmed | AF11: Flexibility for any shift is stated; relocatability is mentioned | AG11: Supplier selection/contracts for spot buys, procurement transactions, SLA/accuracy, supplier/catalog records, issue tracking and reports. | AH11: CV aligns on vendor contact, supplier restocking, documentation, data accuracy and coordinating under time pressure. | AI11: Job explicitly mentions Ariba/SAP and flexible shifts/relocation. CV does not list these systems; decide whether relocation is acceptable. | AJ11: https://www.accenture.com/in-en/careers/jobdetails?id=AIOC-S01660205_en | AK11: https://www.accenture.com/in-en/careers/jobdetails?id=AIOC-S01660205_en | AL11: https://www.glassdoor.co.in/job-listing/procurement-operations-new-associate-accenture-JV_IC2940587_KO0%2C36_KE37%2C46.htm?jl=1010225238230 | AM11: High–medium | AN11: Apply if shift and work location are acceptable; ask what level of SAP/Ariba knowledge is required at entry. | AO11: Not Started | AP11: Not Contacted
A12: LIVE-002 | B12: 8 | C12: P1 – Apply first | D12: =ROUND(E12*0.35+F12*0.25+G12*0.15+H12*0.15+I12*0.05+J12*0.05,1) | E12: 93 | F12: 94 | G12: 96 | H12: 100 | I12: 20 | J12: 35 | K12: Allegis Global Solutions | L12: Onboarding Associate – Meta (Global) – Supply Chain / SCM | M12: Supplier onboarding / compliance operations | N12: 744000151812601 | P12: Official SmartRecruiters ATS ID | Q12: A – official employer ATS posting found current today; recheck before referral | R12: Not stated in posting; official ATS page crawled 11 Oct 2026 | S12: 46306 | T12: Bengaluru | U12: Hybrid (Mon–Wed per posting) | V12: Full-time | W12: Prior similar experience is an advantage; internship/project/coordination experience considered | X12: Bachelor’s degree or equivalent business experience | Y12: Not disclosed on role page | Z12: No reliable job-specific public estimate found | AA12: Not disclosed on role page | AB12: Not disclosed | AC12: Not disclosed on target role page; confirm with recruiter | AD12: Not disclosed on target role page | AE12: Transport/cab/meal benefits not disclosed on target role page | AF12: 3:00 PM–12:00 AM; occasional flexibility may be required | AG12: Supplier onboarding, documentation/compliance checks, tracking, issue escalation, dashboards, audits and stakeholder follow-ups. | AH12: Direct transfer from data checks, vendor communication, inventory records, and coordinating event vendors/teams. | AI12: Late shift until midnight; no formal VMS or procurement-system experience stated on CV. | AJ12: https://jobs.smartrecruiters.com/allegisglobalsolutions/744000151812601 | AK12: https://jobs.smartrecruiters.com/allegisglobalsolutions/744000151812601 | AM12: High – official ATS page with responsibilities and shift | AN12: Apply only if late shift fits; ask employee referral using ATS ID 744000151812601; confirm transport and benefits. | AO12: Not Started | AP12: Not Contacted | AR12: Same general job family as LIVE-001, but shift is later; compare schedules before choosing.
A13: LIVE-036 | B13: 9 | C13: P1 – Apply first | D13: =ROUND(E13*0.35+F13*0.25+G13*0.15+H13*0.15+I13*0.05+J13*0.05,1) | E13: 88 | F13: 100 | G13: 90 | H13: 85 | I13: 100 | J13: 20 | K13: Nathaniel School of Music | L13: Student Support & Operations Executive – Fresher | M13: Student operations / customer support / admin | O13: 1790600518 | P13: Internshala listing reference/slug suffix; not internal requisition | Q13: C – detailed Internshala listing with deadline and one opening | R13: Posted 1 week ago; apply by 28 Oct 2026; 519 applicants at detail retrieval | S13: 46306 | T13: Bengaluru | U13: On-site at studio | V13: Full-time | W13: No experience required; starts immediately | X13: Graduation; exact specific major not restricted in retrieved text | Y13: ₹3,60,000–₹4,20,000/year listed; breakup not shown | Z13: Advertised annual salary, not an independently confirmed CTC | AA13: No variable/bonus disclosed | AB13: No joining bonus disclosed | AC13: Not disclosed | AD13: Not disclosed | AE13: No travel/cab/meal benefit listed | AF13: Monday–Saturday, 9 AM–5 PM; weekends are working days | AG13: Handle calls and queries from students; support admissions/onboarding, portal access and basic tech issues; communicate fees/GST invoices; keep records accurate; coordinate workshops/classes. | AH13: CV fits student records, event logistics, check-ins, customer relations and operational accuracy. | AI13: Customer-facing calls and fee communication are core; six-day onsite week; 519 applicants recorded. Prepare customer-service examples and ask about weekly off and insurance. | AJ13: https://internshala.com/job/detail/fresher-student-support-operations-executive-job-in-bangalore-at-nathaniel-school-of-music1790600518/ | AK13: https://internshala.com/job/detail/fresher-student-support-operations-executive-job-in-bangalore-at-nathaniel-school-of-music1790600518/ | AM13: Medium-high – exact pay, schedule, duties and deadline | AN13: Apply by 28 Oct if comfortable with student calls and six-day onsite schedule; tailor operations support and customer service. | AO13: Not Started | AP13: Not Contacted
A14: LIVE-006 | B14: 10 | C14: P2 – Apply / verify | D14: =ROUND(E14*0.35+F14*0.25+G14*0.15+H14*0.15+I14*0.05+J14*0.05,1) | E14: 88 | F14: 96 | G14: 84 | H14: 100 | I14: 50 | J14: 55 | K14: Accenture | L14: Procure to Pay Operations New Associate – Invoice Processing | M14: P2P / accounts payable support | N14: AIOC-S01660181 | P14: Official Accenture requisition ID | Q14: B – official listing recently indexed; recheck current Apply state | R14: Posting date not shown; official listing crawled about one week before snapshot | S14: 46306 | T14: Bengaluru | U14: Not specified | V14: Full-time | W14: 0–1 years; description notes professional experience 0–3 years | X14: Any Graduation | Y14: Not disclosed by employer | Z14: ₹2–5 LPA broad external estimates for related entry-level procurement/P2P roles; conflicting sources, not an employer offer | AA14: Not disclosed for this requisition | AB14: Not disclosed | AC14: Accenture India company-wide medical benefit described; exact plan not role-specific | AD14: State-based PTO and 10 public holidays described company-wide | AE14: Not disclosed | AF14: Rotational shifts may be required | AG14: Invoice validation and processing, two-way/three-way match concepts, PO/non-PO, vendor payments, finance operations, records and accuracy. | AH14: Relevant transferable evidence: spreadsheet checks, error/documentation discipline, inventory and delivery-receipt verification. | AI14: No formal accounting/AP experience or ERP use on CV. Review invoice, PO, GRN, TAT and reconciliation concepts. | AJ14: https://www.accenture.com/in-en/careers/jobdetails?id=AIOC-S01660181_en | AK14: https://www.accenture.com/in-en/careers/jobdetails?id=AIOC-S01660181_en | AL14: https://www.glassdoor.co.in/Salary/Accenture-Procure-to-Pay-Operations-New-Associate-Salaries-E4138_D_KO10%2C49.htm | AM14: High–medium; exact post date not shown | AN14: Apply and ask if BBA International Business is accepted; practice invoice-match examples. | AO14: Not Started | AP14: Not Contacted
A15: LIVE-008 | B15: 11 | C15: P2 – Apply / verify | D15: =ROUND(E15*0.35+F15*0.25+G15*0.15+H15*0.15+I15*0.05+J15*0.05,1) | E15: 88 | F15: 94 | G15: 70 | H15: 100 | I15: 60 | J15: 55 | K15: Accenture | L15: Procurement Operations New Associate | M15: Procurement operations | N15: AIOC-S01660136 | P15: Official Accenture requisition ID | Q15: B – official job record found recently, but older indexed result; confirm current Apply page | R15: Posting date not shown; result crawled about two weeks before snapshot | S15: 46306 | T15: Bengaluru | U15: Not specified | V15: Full-time | W15: 0–1 years; page header says 0–2 years | X15: BCom / Any Graduation / B.B.M as stated | Y15: Not disclosed by employer | Z15: ₹3–5 LPA estimated by Glassdoor for a related procurement new-associate listing; not an employer offer | AA15: Company-wide bonus program described, role specific unknown | AB15: Not disclosed | AC15: Company-wide medical benefit described; exact role cover unknown | AD15: State-based PTO and 10 public holidays on company-wide policy | AE15: Not disclosed | AF15: Rotational shift status must be confirmed | AG15: Procurement management support, supplier selection, records and PO/process support. | AH15: Transferable experience in inventory, supplier restocking, record checks and Excel. | AI15: The page qualification lists Any Graduation, so likely applicable to BBA; verify the requisition has not closed. SAP/Ariba may be preferred. | AJ15: https://www.accenture.com/in-en/careers/jobdetails?id=AIOC-S01660136_en | AK15: https://www.accenture.com/in-en/careers/jobdetails?id=AIOC-S01660136_en | AL15: https://www.glassdoor.co.in/job-listing/procurement-operations-new-associate-accenture-JV_IC2940587_KO0%2C36_KE37%2C46.htm?jl=1010225238230 | AM15: High–medium – official careers record was indexed two weeks ago | AN15: Check Apply status first, then submit; keep another newer Accenture requisition as priority. | AO15: Not Started | AP15: Not Contacted
A16: LIVE-026 | B16: 12 | C16: P2 – Apply / verify | D16: =ROUND(E16*0.35+F16*0.25+G16*0.15+H16*0.15+I16*0.05+J16*0.05,1) | E16: 93 | F16: 100 | G16: 60 | H16: 75 | I16: 85 | J16: 20 | K16: FreshToHome | L16: Inventory Intern | M16: Inventory / fulfilment / warehouse coordination | O16: Apna 281485233 | P16: Public Apna job ID | Q16: C – current job-board listing; verify internship status and availability | R16: Posted date not shown; returned in Apna Bengaluru fresher search 11 Oct 2026 | S16: 46306 | T16: Bengaluru | U16: Warehouse/fulfilment setting implied; exact mode not stated | V16: Internship | W16: Freshers only | X16: Graduate | Y16: ₹15,000/month stipend listed (not permanent-job CTC) | Z16: ₹1.8 L/year equivalent only if paid for 12 months; not CTC or guaranteed duration | AA16: Not disclosed | AB16: Not disclosed | AC16: Not disclosed | AD16: Not disclosed | AE16: Not disclosed | AF16: Work hours/weekly off not stated | AG16: Monitor daily warehouse/fulfilment inventory; track inward/outward/transfers/returns/adjustments; coordinate procurement, warehouse, category, planning and logistics; reconcile PO/GRN/invoices and inventory transactions. | AH16: Excellent direct match for Aero India inventory tracking, family-store restocking, receipt verification and operations/data checking. | AI16: Internship length, stipend conditions, conversion, working hours and transport are undisclosed; confirm whether full-time offer is possible. | AJ16: https://apna.co/job/bengaluru-bangalore/inventory-intern-281485233 | AK16: https://www.freshtohome.com/ | AL16: https://apna.co/job/bengaluru-bangalore/inventory-intern-281485233 | AM16: Medium – board lists graduate/fresher and stipend | AN16: Apply if internship acceptable; ask term/duration, stipend payout timing, weekly off, transport and PPO conversion. | AO16: Not Started | AP16: Not Contacted
A17: LIVE-027 | B17: 13 | C17: P2 – Apply / verify | D17: =ROUND(E17*0.35+F17*0.25+G17*0.15+H17*0.15+I17*0.05+J17*0.05,1) | E17: 88 | F17: 100 | G17: 60 | H17: 75 | I17: 85 | J17: 20 | K17: More Retail | L17: Retail Management Trainee – Fresher | M17: Retail/store operations / inventory | O17: Apna 113086955 | P17: Public Apna job ID | Q17: C – public job-board result; verify active application on More Retail careers | R17: Posted date not displayed; current result returned 11 Oct 2026 | S17: 46306 | T17: Bengaluru | U17: Store/site-based implied | V17: Full-time / trainee | W17: Graduate fresher under 28 per public listing | X17: Graduate | Y17: ₹24,000/month listed; annualised ₹2.88 LPA if paid 12 months, not verified CTC | Z17: Monthly pay is job-board listing information; not an employer offer letter | AA17: Not disclosed | AB17: Not disclosed | AC17: Not disclosed | AD17: Not disclosed | AE17: Not disclosed | AF17: Retail shift and weekly-off pattern not disclosed | AG17: Retail/store operations, customer experience, inventory/stock management, team management, cashiering and retail systems; listing says potential Duty Manager in 3 months. | AH17: Direct store-assistant experience, billing/cash register, restocking, customer handling and team event operations. | AI17: Retail role may include customer service and sales-related KPIs; confirm shift/weekly off, target requirements and location. | AJ17: https://apna.co/job/bengaluru-bangalore/fresher-retail-managament-trainee-113086955 | AK17: https://moreretail.com/ | AL17: https://apna.co/job/bengaluru-bangalore/fresher-retail-managament-trainee-113086955 | AM17: Medium – job board describes fresher programme and compensation | AN17: Apply if retail operations and store work suit you; ask what training, transfer policy and weekly offs mean. | AO17: Not Started | AP17: Not Contacted
A18: LIVE-032 | B18: 14 | C18: P2 – Apply / verify | D18: =ROUND(E18*0.35+F18*0.25+G18*0.15+H18*0.15+I18*0.05+J18*0.05,1) | E18: 90 | F18: 94 | G18: 60 | H18: 75 | I18: 85 | J18: 20 | K18: BAL Corporate Services OPC | L18: Supply Chain Executive | M18: Supply chain coordination | O18: Apna 911487320 | P18: Public Apna job ID | Q18: C – board says freshers can apply; check official company/recruiter details | R18: Posted date not displayed; current fresher search returned 11 Oct 2026 | S18: 46306 | T18: JP Nagar, Bengaluru | U18: Not stated | V18: Full-time | W18: Freshers can apply per Apna listing | X18: Graduate | Y18: ₹17,000–₹25,000/month listed; annualised ₹2.04–₹3.00 LPA if paid 12 months; not employer-verified CTC | Z18: No separate CTC breakdown; annualised figure is arithmetic from monthly listing, not CTC | AA18: Not disclosed | AB18: Not disclosed | AC18: Not disclosed | AD18: Not disclosed | AE18: Not disclosed | AF18: Not disclosed | AG18: Day-to-day supply chain operation management, vendor relations, process optimization and coordination. | AH18: Strong match with supplier restocking, delivery receipt checks, inventory control, vendor coordination and Excel records. | AI18: Employer profile and job conditions need verification. Ask whether the role is procurement, field-facing, sales-linked or shift-based. | AJ18: https://apna.co/job/bengaluru-bangalore/supply-chain-executive-911487320 | AK18: Not independently verified in this pass | AL18: https://apna.co/job/bengaluru-bangalore/supply-chain-executive-911487320 | AM18: Medium – board exposes salary and fresher eligibility | AN18: Apply if company details check out; request written CTC break-up, location, benefits and work schedule. | AO18: Not Started | AP18: Not Contacted
A19: LIVE-010 | B19: 15 | C19: P2 – Apply / verify | D19: =ROUND(E19*0.35+F19*0.25+G19*0.15+H19*0.15+I19*0.05+J19*0.05,1) | E19: 86 | F19: 62 | G19: 96 | H19: 100 | I19: 50 | J19: 55 | K19: Accenture | L19: Procure to Pay Operations New Associate – Account Management | M19: P2P / finance operations | N19: AIOC-S01668841 | P19: Official Accenture requisition ID | Q19: A – official listing found current today; note qualification wording before applying | R19: Posting date not shown; official listing crawled 11 Oct 2026 | S19: 46306 | T19: Bengaluru | U19: May require rotational shifts | V19: Full-time | W19: 0–1 years; page header says 0–2 years | X19: BCom / B.B.M as stated (does not explicitly say any graduation) | Y19: Not disclosed by employer | Z19: Public estimates for related P2P roles range roughly ₹2–5 LPA across different sources; uncertain and not an offer | AA19: Not disclosed for this req | AB19: Not disclosed | AC19: Company-wide medical cover exists; role specific eligibility unknown | AD19: Company-wide PTO policy; role-specific details unknown | AE19: Not disclosed | AF19: Rotational shifts may be required | AG19: Finance operations, vendor compliance, invoices, PO/non-PO, invoice matching, requisitioning and payment-processing tasks. | AH19: CV aligns on records, accuracy, supplier coordination and transaction-related documentation. | AI19: Degree wording lists BCom/B.B.M; BBA International Business is not explicitly named. Ask recruiting team to confirm eligibility before applying. | AJ19: https://www.accenture.com/in-en/careers/jobdetails?id=AIOC-S01668841_en | AK19: https://www.accenture.com/in-en/careers/jobdetails?id=AIOC-S01668841_en | AL19: https://www.glassdoor.co.in/Salary/Accenture-Procure-to-Pay-Operations-New-Associate-Salaries-E4138_D_KO10%2C49.htm | AM19: High – official page current today, eligibility wording ambiguous | AN19: Message Accenture recruiter first to confirm BBA eligibility; if yes, apply and quote requisition ID. | AO19: Not Started | AP19: Not Contacted
A20: LIVE-009 | B20: 16 | C20: P3 – Conditional / verify | D20: =ROUND(E20*0.35+F20*0.25+G20*0.15+H20*0.15+I20*0.05+J20*0.05,1) | E20: 87 | F20: 95 | G20: 50 | H20: 100 | I20: 60 | J20: 55 | K20: Accenture | L20: Procurement Operations New Associate | M20: Procurement operations | N20: AIOC-S01660203 | P20: Official Accenture requisition ID | Q20: C – official job record indexed last month; availability may be stale; test Apply before tailoring | R20: Posting date not shown; result crawled last month | S20: 46306 | T20: Bengaluru | U20: Flexible shifts mentioned | V20: Full-time | W20: 0–1 years | X20: Any Graduation | Y20: Not disclosed by employer | Z20: ₹3–5 LPA estimated for similar role by Glassdoor; not an employer offer | AA20: Company-wide bonus programme described; role-specific eligibility unknown | AB20: Not disclosed | AC20: Company-wide medical cover described; role-specific terms unknown | AD20: State-based PTO and 10 public holidays per company-wide page | AE20: Not disclosed | AF20: Flexible shifts; exact shift unknown | AG20: Spot-buy procurement, supplier records and transactional procurement support. | AH20: Vendor coordination, inventory, documentation and spreadsheet accuracy are transferable. | AI20: Older indexed result; verify active status before asking for employee referral; SAP/Ariba requirements should be reviewed. | AJ20: https://www.accenture.com/in-en/careers/jobdetails?id=AIOC-S01660203_en | AK20: https://www.accenture.com/in-en/careers/jobdetails?id=AIOC-S01660203_en | AL20: https://www.glassdoor.co.in/job-listing/procurement-operations-new-associate-accenture-JV_IC2940587_KO0%2C36_KE37%2C46.htm?jl=1010225238230 | AM20: Medium – older search index | AN20: Only apply after confirming it remains live; do not rely on an old cached listing. | AO20: Not Started | AP20: Not Contacted
A21: LIVE-037 | B21: 17 | C21: P3 – conditional; sales-heavy | D21: =ROUND(E21*0.35+F21*0.25+G21*0.15+H21*0.15+I21*0.05+J21*0.05,1) | E21: 60 | F21: 100 | G21: 97 | H21: 85 | I21: 100 | J21: 60 | K21: Soul Staje | L21: Operations Manager – Fresher (Operations & Sales) | M21: Event venue operations / events / sales | O21: 1791557235 | P21: Internshala listing reference/slug suffix; not internal requisition | Q21: C – current detailed Internshala listing; employer asks Bangalore-only candidates | R21: Posted 2 days ago; apply by 8 Nov 2026; one opening; early applicant when retrieved | S21: 46306 | T21: Bengaluru | U21: On-site creative venue | V21: Full-time | W21: No experience required per listing; starts immediately | X21: No degree restriction shown in retrieved details; Bangalore-only | Y21: Annual CTC ₹2.6–3.9 LPA: fixed ₹2.0–2.7 LPA + variable ₹0.6–1.2 LPA linked to sales/bookings | Z21: Advertised CTC break-up from listing; variable component is significant | AA21: Sales incentives/variable pay on successful bookings; not a joining bonus | AB21: No joining bonus disclosed | AC21: No insurance details disclosed | AD21: Leave/holidays not disclosed | AE21: Travel/cab/meal not disclosed | AF21: 10 AM–7 PM; weekends working; one weekday off | AG21: Day-to-day venue operations and vendor coordination, event planning/execution, on-ground coordination, client/renter management, proactive outreach, lead generation and converting event/venue bookings. | AH21: Strong evidence: event coordination, vendor setup, schedules, on-ground volunteer supervision and managing visitors/events. | AI21: Role explicitly includes sales/business development, lead generation and bookings; not ideal if avoiding sales. Variable CTC is 0.6–1.2 LPA; clarify targets/incentives. | AJ21: https://internshala.com/job/detail/fresher-operations-manager-job-in-bangalore-at-soul-staje1791557235/ | AK21: https://internshala.com/job/detail/fresher-operations-manager-job-in-bangalore-at-soul-staje1791557235/ | AM21: Medium-high – exact CTC break-up, working hours and duties are visible | AN21: Only apply if open to sales targets and weekend work; ask target definitions, incentive payout, lead source and fixed pay in offer letter. | AO21: Not Started | AP21: Not Contacted
A22: LIVE-025 | B22: 18 | C22: P3 – Conditional / verify | D22: =ROUND(E22*0.35+F22*0.25+G22*0.15+H22*0.15+I22*0.05+J22*0.05,1) | E22: 91 | F22: 100 | G22: 60 | H22: 75 | I22: 20 | J22: 20 | K22: Marriott Hotels India | L22: Purchase Associate | M22: Purchasing / hotel inventory | O22: Apna 1912459795 | P22: Public Apna job ID; internal req not verified | Q22: C – current board result; verify company portal/HR status | R22: Posted date not displayed; fresher listing returned 11 Oct 2026 | S22: 46306 | T22: Bengaluru | U22: Likely hotel/site-based; not explicitly stated | V22: Full-time | W22: Freshers only per Apna listing | X22: Degree not specified in retrieved detail | Y22: Not disclosed | Z22: No reliable role-specific estimate verified | AA22: Not disclosed | AB22: Not disclosed | AC22: Target role page does not state insurance; confirm with hotel HR | AD22: Not disclosed | AE22: Transport/meal/travel allowance not disclosed | AF22: Work hours/weekly off not stated | AG22: Food inventory/order/cost counts, record keeping and invoices, inventory audits, requisitions, stock levels, delivery receipt tracking, invoice reconciliation and supplier delivery issues. | AH22: Excellent role-specific transfer from retail inventory, supplier restocking, billing and incoming delivery verification. | AI22: Need confirm required qualification, shifts, hotel-specific benefits and internal job ID. Public Apna ID is not Marriott requisition. | AJ22: https://apna.co/job/bengaluru-bangalore/purchase-associate-1912459795 | AK22: https://careers.marriott.com/ | AL22: https://apna.co/job/bengaluru-bangalore/purchase-associate-1912459795 | AM22: Medium – public job board with detailed responsibilities | AN22: Apply if job remains available; ask Marriott HR for internal req ID, CTC, service charge/tips eligibility if applicable, insurance, meals and weekly offs. | AO22: Not Started | AP22: Not Contacted
A23: LIVE-012 | B23: 19 | C23: P3 – Conditional / verify | D23: =ROUND(E23*0.35+F23*0.25+G23*0.15+H23*0.15+I23*0.05+J23*0.05,1) | E23: 80 | F23: 74 | G23: 90 | H23: 100 | I23: 20 | J23: 20 | K23: EY | L23: Associate – Resource Management | M23: Resource management / workforce scheduling | N23: 1739823 | P23: Official EY requisition ID | Q23: B – official EY listing referenced as recent; recheck application state | R23: Reported posted 8 Oct 2026 in listing snapshot; confirm current role page | S23: 46306 | T23: Bengaluru | U23: Not disclosed | V23: Full-time | W23: 0–3 years of relevant/resource-management exposure described in listing data; verify exact requirements | X23: Graduate degree; advanced Excel requested in listing data | Y23: Not disclosed by employer | Z23: No reliable official CTC range found | AA23: Role-specific bonus not disclosed | AB23: Not disclosed | AC23: Role-specific medical/insurance details not retrieved | AD23: Leave policy not retrieved from role page | AE23: Transport/travel reimbursement not disclosed | AF23: Exact work hours/weekly offs not disclosed | AG23: Resource scheduling, resolving scheduling conflicts, handling requests, utilisation/reporting and stakeholder coordination. | AH23: CV supports scheduling through artist/volunteer schedules, coordination and Excel-based record work. | AI23: Advanced Excel/resource-management tools may be expected; CV says formulas/data verification but not advanced PivotTables/Power Query. Verify the exact degree/experience wording. | AJ23: https://careers.ey.com/ey/job/Bengaluru-Associate-Resource-Management-KA-560048/1445690033/ | AK23: https://careers.ey.com/ey/job/Bengaluru-Associate-Resource-Management-KA-560048/1445690033/ | AM23: Medium-high – official careers URL; salary and benefits not disclosed | AN23: Apply if the role accepts your current level; prepare Excel/scheduling example and ask about shifts and benefits. | AO23: Not Started | AP23: Not Contacted
A24: LIVE-029 | B24: 20 | C24: P3 – Conditional / verify | D24: =ROUND(E24*0.35+F24*0.25+G24*0.15+H24*0.15+I24*0.05+J24*0.05,1) | E24: 89 | F24: 92 | G24: 60 | H24: 75 | I24: 20 | J24: 20 | K24: Intugine Technologies | L24: Operations Intern – Reverse Logistics | M24: Reverse logistics / supply chain visibility | O24: Apna 1694554752 | P24: Public Apna job ID | Q24: C – current board listing; verify official company careers/HR link | R24: Posted date not shown; returned in Apna fresher search 11 Oct 2026 | S24: 46306 | T24: Bengaluru | U24: Not stated | V24: Internship | W24: Freshers only per Apna listing | X24: Not fully specified in retrieved excerpt | Y24: Not disclosed | Z24: No reliable role-specific estimate verified | AA24: Not disclosed | AB24: Not disclosed | AC24: Not disclosed | AD24: Not disclosed | AE24: Not disclosed | AF24: Not disclosed | AG24: Internship related to reverse-logistics supply chain processes and improving operational visibility for brand shipments; exact duties to verify from full listing. | AH24: Direct transfer from logistics/travel scheduling for events, inventory control, data accuracy and AI operations datasets. | AI24: No stipend or duration captured; ask for internship term, stipend, conversion and tools used. | AJ24: https://apna.co/job/bengaluru-bangalore/operations-intern-reverse-logistics-1694554752 | AK24: https://intugine.com/careers/ | AL24: https://apna.co/job/bengaluru-bangalore/operations-intern-reverse-logistics-1694554752 | AM24: Medium – public board record | AN24: Apply and contact operations team for a paid internship, duration, work hours and PPO possibilities. | AO24: Not Started | AP24: Not Contacted
A25: LIVE-013 | B25: 21 | C25: P3 – Conditional / verify | D25: =ROUND(E25*0.35+F25*0.25+G25*0.15+H25*0.15+I25*0.05+J25*0.05,1) | E25: 78 | F25: 62 | G25: 100 | H25: 100 | I25: 20 | J25: 50 | K25: Amazon | L25: Senior Associate – Catalog, RBS | M25: Catalog operations / content and data support | N25: 10574278 | P25: Official Amazon job ID | Q25: A/B – official Amazon search page showed the role as a current result; use exact Job ID to open/apply | R25: Posted 9 Oct 2026; official Amazon search result updated about 2 hours after retrieval | S25: 46306 | T25: Bengaluru – Virtual listed on Amazon search result | U25: Virtual/remote label on search result; confirm exact work arrangement | V25: Full-time | W25: Experience requirement not displayed in search snippet; title includes Senior Associate, so verify before applying | X25: Bachelor’s degree; strong written/verbal English and data-backed updates | Y25: Not disclosed by employer | Z25: No reliable role-specific estimate verified | AA25: Not disclosed | AB25: Not disclosed | AC25: Amazon company benefits page describes medical and accident protection; actual eligibility depends on country, role and employment status | AD25: Amazon benefits page describes paid time off and paid holidays; India role details must be confirmed | AE25: Not disclosed | AF25: Shift/weekends not stated in search snippet | AG25: Search-result evidence establishes catalog/RBS role title and writing/data-backed communication requirement; detailed duties require opening full posting. | AH25: Potential fit: data checking, structured spreadsheets, written documentation and digital operations portfolio. | AI25: Senior Associate title may imply experience not visible in search snippet; get full criteria before applying. Direct application path not confirmed; use official job-search page and exact Job ID. | AJ25: https://www.amazon.jobs/en/search?city%5B%5D=Bengaluru&distanceType=Mi&industry_experience=less_than_1_year&radius=24km&result_limit=10 | AK25: https://www.amazon.jobs/en/search?city%5B%5D=Bengaluru&distanceType=Mi&industry_experience=less_than_1_year&radius=24km&result_limit=10 | AL25: https://www.amazon.jobs/content/en/benefits | AM25: High current listing / medium eligibility – direct role details incomplete | AN25: Search the Amazon careers page for job ID 10574278; open full role requirements before applying. Ask an Amazon employee to use the exact ID. | AO25: Not Started | AP25: Not Contacted
A26: LIVE-014 | B26: 22 | C26: P3 – Conditional / verify | D26: =ROUND(E26*0.35+F26*0.25+G26*0.15+H26*0.15+I26*0.05+J26*0.05,1) | E26: 78 | F26: 62 | G26: 100 | H26: 100 | I26: 20 | J26: 50 | K26: Amazon | L26: Senior Associate – Catalog, RBS | M26: Catalog operations / content and data support | N26: 10574277 | P26: Official Amazon job ID | Q26: A/B – official Amazon search page showed the role as a current result; use exact Job ID to open/apply | R26: Posted 9 Oct 2026; official Amazon search result updated about 2 hours after retrieval | S26: 46306 | T26: Bengaluru – Virtual listed on Amazon search result | U26: Virtual/remote label on search result; confirm exact work arrangement | V26: Full-time | W26: Experience requirement not displayed in search snippet; title includes Senior Associate, so verify before applying | X26: Bachelor’s degree; strong written/verbal English and data-backed updates | Y26: Not disclosed by employer | Z26: No reliable role-specific estimate verified | AA26: Not disclosed | AB26: Not disclosed | AC26: Amazon company benefits page describes medical and accident protection; actual eligibility depends on country, role and employment status | AD26: Amazon benefits page describes paid time off and paid holidays; India role details must be confirmed | AE26: Not disclosed | AF26: Shift/weekends not stated in search snippet | AG26: Search-result evidence establishes catalog/RBS role title and writing/data-backed communication requirement; detailed duties require opening full posting. | AH26: Potential fit: data checking, structured spreadsheets, written documentation and digital operations portfolio. | AI26: Senior Associate title may imply experience not visible in search snippet; get full criteria before applying. Direct application path not confirmed; use official job-search page and exact Job ID. | AJ26: https://www.amazon.jobs/en/search?city%5B%5D=Bengaluru&distanceType=Mi&industry_experience=less_than_1_year&radius=24km&result_limit=10 | AK26: https://www.amazon.jobs/en/search?city%5B%5D=Bengaluru&distanceType=Mi&industry_experience=less_than_1_year&radius=24km&result_limit=10 | AL26: https://www.amazon.jobs/content/en/benefits | AM26: High current listing / medium eligibility – direct role details incomplete | AN26: Search the Amazon careers page for job ID 10574277; open full role requirements before applying. Ask an Amazon employee to use the exact ID. | AO26: Not Started | AP26: Not Contacted
A27: LIVE-015 | B27: 23 | C27: P3 – Conditional / verify | D27: =ROUND(E27*0.35+F27*0.25+G27*0.15+H27*0.15+I27*0.05+J27*0.05,1) | E27: 78 | F27: 62 | G27: 100 | H27: 100 | I27: 20 | J27: 50 | K27: Amazon | L27: Senior Associate – Catalog, RBS | M27: Catalog operations / content and data support | N27: 10574276 | P27: Official Amazon job ID | Q27: A/B – official Amazon search page showed the role as a current result; use exact Job ID to open/apply | R27: Posted 9 Oct 2026; official Amazon search result updated about 2 hours after retrieval | S27: 46306 | T27: Bengaluru – Virtual listed on Amazon search result | U27: Virtual/remote label on search result; confirm exact work arrangement | V27: Full-time | W27: Experience requirement not displayed in search snippet; title includes Senior Associate, so verify before applying | X27: Bachelor’s degree; strong written/verbal English and data-backed updates | Y27: Not disclosed by employer | Z27: No reliable role-specific estimate verified | AA27: Not disclosed | AB27: Not disclosed | AC27: Amazon company benefits page describes medical and accident protection; actual eligibility depends on country, role and employment status | AD27: Amazon benefits page describes paid time off and paid holidays; India role details must be confirmed | AE27: Not disclosed | AF27: Shift/weekends not stated in search snippet | AG27: Search-result evidence establishes catalog/RBS role title and writing/data-backed communication requirement; detailed duties require opening full posting. | AH27: Potential fit: data checking, structured spreadsheets, written documentation and digital operations portfolio. | AI27: Senior Associate title may imply experience not visible in search snippet; get full criteria before applying. Direct application path not confirmed; use official job-search page and exact Job ID. | AJ27: https://www.amazon.jobs/en/search?city%5B%5D=Bengaluru&distanceType=Mi&industry_experience=less_than_1_year&radius=24km&result_limit=10 | AK27: https://www.amazon.jobs/en/search?city%5B%5D=Bengaluru&distanceType=Mi&industry_experience=less_than_1_year&radius=24km&result_limit=10 | AL27: https://www.amazon.jobs/content/en/benefits | AM27: High current listing / medium eligibility – direct role details incomplete | AN27: Search the Amazon careers page for job ID 10574276; open full role requirements before applying. Ask an Amazon employee to use the exact ID. | AO27: Not Started | AP27: Not Contacted
A28: LIVE-016 | B28: 24 | C28: P3 – Conditional / verify | D28: =ROUND(E28*0.35+F28*0.25+G28*0.15+H28*0.15+I28*0.05+J28*0.05,1) | E28: 78 | F28: 62 | G28: 100 | H28: 100 | I28: 20 | J28: 50 | K28: Amazon | L28: Senior Associate – Catalog, RBS | M28: Catalog operations / content and data support | N28: 10574272 | P28: Official Amazon job ID | Q28: A/B – official Amazon search page showed the role as a current result; use exact Job ID to open/apply | R28: Posted 9 Oct 2026; official Amazon search result updated about 2 hours after retrieval | S28: 46306 | T28: Bengaluru – Virtual listed on Amazon search result | U28: Virtual/remote label on search result; confirm exact work arrangement | V28: Full-time | W28: Experience requirement not displayed in search snippet; title includes Senior Associate, so verify before applying | X28: Bachelor’s degree; strong written/verbal English and data-backed updates | Y28: Not disclosed by employer | Z28: No reliable role-specific estimate verified | AA28: Not disclosed | AB28: Not disclosed | AC28: Amazon company benefits page describes medical and accident protection; actual eligibility depends on country, role and employment status | AD28: Amazon benefits page describes paid time off and paid holidays; India role details must be confirmed | AE28: Not disclosed | AF28: Shift/weekends not stated in search snippet | AG28: Search-result evidence establishes catalog/RBS role title and writing/data-backed communication requirement; detailed duties require opening full posting. | AH28: Potential fit: data checking, structured spreadsheets, written documentation and digital operations portfolio. | AI28: Senior Associate title may imply experience not visible in search snippet; get full criteria before applying. Direct application path not confirmed; use official job-search page and exact Job ID. | AJ28: https://www.amazon.jobs/en/search?city%5B%5D=Bengaluru&distanceType=Mi&industry_experience=less_than_1_year&radius=24km&result_limit=10 | AK28: https://www.amazon.jobs/en/search?city%5B%5D=Bengaluru&distanceType=Mi&industry_experience=less_than_1_year&radius=24km&result_limit=10 | AL28: https://www.amazon.jobs/content/en/benefits | AM28: High current listing / medium eligibility – direct role details incomplete | AN28: Search the Amazon careers page for job ID 10574272; open full role requirements before applying. Ask an Amazon employee to use the exact ID. | AO28: Not Started | AP28: Not Contacted
A29: LIVE-030 | B29: 25 | C29: P3 – Conditional / verify | D29: =ROUND(E29*0.35+F29*0.25+G29*0.15+H29*0.15+I29*0.05+J29*0.05,1) | E29: 88 | F29: 93 | G29: 60 | H29: 75 | I29: 20 | J29: 20 | K29: Ninjacart | L29: Intern – Agri Supply Chain Operations | M29: Supply chain / fulfilment / agri-tech | O29: Apna 1678018202 | P29: Public Apna job ID | Q29: C – current board listing; verify official internship opening | R29: Posted date not shown; returned in Apna fresher search 11 Oct 2026 | S29: 46306 | T29: Bengaluru | U29: Not stated | V29: Internship | W29: Freshers only per Apna listing | X29: Not fully specified | Y29: Not disclosed | Z29: No reliable role-specific estimate verified | AA29: Not disclosed | AB29: Not disclosed | AC29: Not disclosed | AD29: Not disclosed | AE29: Not disclosed | AF29: Not disclosed | AG29: Agri-supply chain internship associated with Ninjamandi; supply-chain coordination across traders/retailers and fulfilment ecosystem. Confirm exact tasks in official application. | AH29: Inventory, supplier communication, retail operations and event logistics are highly transferable. | AI29: Duration, stipend, shifts, locations and PPO status not disclosed in current captured data. | AJ29: https://apna.co/job/bengaluru-bangalore/intern-agri-supply-chain-operations-1678018202 | AK29: https://ninjacart.com/careers/ | AL29: https://apna.co/job/bengaluru-bangalore/intern-agri-supply-chain-operations-1678018202 | AM29: Medium – public listing with company identity | AN29: Apply if internship accepted; ask stipend, role duration, field/warehouse exposure, travel reimbursements and PPO. | AO29: Not Started | AP29: Not Contacted
A30: LIVE-022 | B30: 26 | C30: P3 – Conditional / verify | D30: =ROUND(E30*0.35+F30*0.25+G30*0.15+H30*0.15+I30*0.05+J30*0.05,1) | E30: 88 | F30: 82 | G30: 60 | H30: 75 | I30: 20 | J30: 60 | K30: J.P. Morgan Services India | L30: Business and Operations Specialist | M30: Business operations / vendor payments | O30: Apna 1129984729 | P30: Public Apna job ID; internal req not verified | Q30: C – current job-board lead; internal JPMC requisition and live apply state not verified | R30: Posted date not shown; returned in Apna Bengaluru fresher search 11 Oct 2026 | S30: 46306 | T30: Bengaluru | U30: Not specified | V30: Full-time | W30: Public board says freshers can apply; confirm official employer requirements | X30: Degree requirement not clear in current board excerpt; confirm on official JPMC portal | Y30: Not disclosed | Z30: No reliable role-specific estimate verified | AA30: Not disclosed | AB30: Not disclosed | AC30: JPMC career page describes employee/family medical benefits and wellness/financial/family benefits; benefits vary by role and location | AD30: Role-specific leave and holiday package not disclosed | AE30: Not disclosed | AF30: Not disclosed | AG30: Invoice and vendor-payment request checks, data quality, query handling, records/trackers, audit readiness, exception resolution and process documentation. | AH30: Strong transfer from data checks, documentation, spreadsheets, delivery receipts and vendor communication. | AI30: Public listing ID is not a JPMC internal requisition; need to match to official JPMC career page. No finance operations experience stated. | AJ30: https://apna.co/job/bengaluru-bangalore/business-and-operations-specialist-1129984729 | AK30: https://www.jpmorganchase.com/careers | AL30: https://apna.co/job/bengaluru-bangalore/business-and-operations-specialist-1129984729 | AM30: Medium – aggregator lists freshers; company req needs verification | AN30: Search official JPMC Careers with exact role title and Bengaluru; request referral only after getting internal job ID. | AO30: Not Started | AP30: Not Contacted
A31: LIVE-031 | B31: 27 | C31: P3 – Conditional / verify | D31: =ROUND(E31*0.35+F31*0.25+G31*0.15+H31*0.15+I31*0.05+J31*0.05,1) | E31: 83 | F31: 96 | G31: 60 | H31: 75 | I31: 20 | J31: 20 | K31: Quess Corp Limited | L31: Procurement Intern | M31: Procurement support | O31: Apna 1210656152 | P31: Public Apna job ID | Q31: C – current job-board listing; verify host/employer and role details | R31: Posted date not shown; returned in Apna fresher search 11 Oct 2026 | S31: 46306 | T31: Bengaluru | U31: Not stated | V31: Internship | W31: Freshers only per Apna listing | X31: Education not specified in retrieved listing | Y31: Not disclosed | Z31: No reliable role-specific estimate verified | AA31: Not disclosed | AB31: Not disclosed | AC31: Not disclosed | AD31: Not disclosed | AE31: Not disclosed | AF31: Not disclosed | AG31: Assist purchasing/supply-chain activities, procurement processes and vendor-management admin tasks. | AH31: Direct transfer from wholesale distributor communication, supplier restocking, inventory control and accurate delivery receipts. | AI31: Stipend, duration and whether Quess is the direct employer or staffing provider need confirmation. | AJ31: https://apna.co/job/bengaluru/intern-procurement-1210656152 | AK31: https://www.quesscorp.com/careers/ | AL31: https://apna.co/job/bengaluru/intern-procurement-1210656152 | AM31: Medium-low – public board listing; staffing/employer details need check | AN31: Ask who the actual host employer is, stipend, duration, location and possible conversion before accepting. | AO31: Not Started | AP31: Not Contacted
A32: LIVE-017 | B32: 28 | C32: P3 – Conditional / verify | D32: =ROUND(E32*0.35+F32*0.25+G32*0.15+H32*0.15+I32*0.05+J32*0.05,1) | E32: 74 | F32: 68 | G32: 76 | H32: 100 | I32: 20 | J32: 50 | K32: Amazon | L32: Associate, Quality Services, ASV | M32: Quality services / data-quality operations | N32: 10557347 | P32: Official Amazon job ID | Q32: B – official Amazon search result listed job; re-open exact ID | R32: Posted 23 Sep 2026; official search result updated 9 days before snapshot | S32: 46306 | T32: Bengaluru | U32: Not disclosed | V32: Full-time | W32: Experience requirement not shown in result snippet | X32: Bachelor’s degree; knowledge of QA methodology and tools | Y32: Not disclosed | Z32: No reliable role-specific estimate verified | AA32: Not disclosed | AB32: Not disclosed | AC32: Amazon company benefits are general and location/role-dependent; target role terms not disclosed | AD32: PTO/paid holidays are described generically by Amazon; India terms require confirmation | AE32: Not disclosed | AF32: Not disclosed | AG32: Quality services role; basic qualifications list a bachelor’s degree and familiarity with QA methodology/tools. | AH32: Instawork data checking and error-documentation experience is a plausible quality-process bridge. | AI32: No formal QA tools or software testing experience stated; confirm whether this is non-technical process QA and which tools are required. | AJ32: https://www.amazon.jobs/en/search?city%5B%5D=Bengaluru&distanceType=Mi&industry_experience=less_than_1_year&radius=24km&result_limit=10 | AK32: https://www.amazon.jobs/en/search?city%5B%5D=Bengaluru&distanceType=Mi&industry_experience=less_than_1_year&radius=24km&result_limit=10 | AL32: https://www.amazon.jobs/content/en/benefits | AM32: High source reliability; moderate role-specific fit | AN32: Open Amazon search and search job ID 10557347; apply only after validating whether work is business/process QA or technical testing. | AO32: Not Started | AP32: Not Contacted
A33: LIVE-033 | B33: 29 | C33: P3 – Conditional / verify | D33: =ROUND(E33*0.35+F33*0.25+G33*0.15+H33*0.15+I33*0.05+J33*0.05,1) | E33: 88 | F33: 72 | G33: 70 | H33: 75 | I33: 20 | J33: 20 | K33: Prosperr.io | L33: Operation Support Associate | M33: Business operations / reports and dashboards | O33: Indeed JOBSEARCH_100695 | P33: Indeed public search token; not employer requisition | Q33: C – recent-enough Indeed listing; official company ATS not matched in current scan | R33: Posted 12 Sep 2026 (Indeed result) | S33: 46306 | T33: Bengaluru | U33: Not stated | V33: Full-time likely; verify | W33: Previous listing data says 0–3 years; current result only confirms job title – reconfirm | X33: Not fully specified | Y33: Not disclosed in current search result; do not rely on older inferred pay without recruiter confirmation | Z33: No reliable official estimate verified | AA33: Not disclosed | AB33: Not disclosed | AC33: Not disclosed | AD33: Not disclosed | AE33: Not disclosed | AF33: Not disclosed | AG33: Support day-to-day business operations, maintain operational data/reports/dashboards and coordinate internal teams. | AH33: Strong transfer from Instawork datasets, spreadsheet validation, discrepancy reporting and dashboard/automation projects. | AI33: Confirm active status, exact eligibility, employment entity, salary and whether job is customer operations or finance operations. | AJ33: https://to.indeed.com/aav8jwsdfpx4 | AK33: https://prosperr.io/careers | AL33: https://to.indeed.com/aav8jwsdfpx4 | AM33: Medium – Indeed lead, employer portal not verified | AN33: Open listing and official company site; apply only if role is genuine/current and responsibilities are operations rather than sales. | AO33: Not Started | AP33: Not Contacted
A34: LIVE-023 | B34: 30 | C34: P3 – Conditional / verify | D34: =ROUND(E34*0.35+F34*0.25+G34*0.15+H34*0.15+I34*0.05+J34*0.05,1) | E34: 85 | F34: 78 | G34: 60 | H34: 75 | I34: 20 | J34: 20 | K34: KPMG India Services | L34: Business Associate – Quality and Risk Management | M34: Quality / risk / due diligence operations | O34: Apna 1779532141 | P34: Public Apna job ID; internal req not verified | Q34: C – fresher-friendly public listing; current employer career requisition not verified | R34: Posted date not shown; returned in Apna Bengaluru fresher search 11 Oct 2026 | S34: 46306 | T34: Bengaluru | U34: Not stated | V34: Full-time | W34: Public board says freshers can apply | X34: Degree requirement not fully specified in retrieved excerpt; confirm official posting | Y34: Not disclosed | Z34: No reliable role-specific estimate verified | AA34: Not disclosed | AB34: Not disclosed | AC34: Not disclosed on exact job listing | AD34: Not disclosed | AE34: Not disclosed | AF34: Global onshore stakeholders; work hours/weekends not stated | AG34: Research/desktop due diligence for international teams; database and company research, regulatory/sanctions screening context, stakeholder updates and project delivery. | AH34: BBA International Business, web research, communication, documentation and accurate data handling transfer well. | AI34: Risk/regulatory screening knowledge is not stated in CV; prepare to learn and explain research methods. Official requisition missing. | AJ34: https://apna.co/job/bengaluru-bangalore/business-associate-quality-and-risk-management-1779532141 | AK34: https://kpmg.com/in/en/home/careers.html | AL34: https://apna.co/job/bengaluru-bangalore/business-associate-quality-and-risk-management-1779532141 | AM34: Medium – public job board only; internal ID not verified | AN34: Find matching KPMG role on the official portal, then ask employee to refer using internal requisition. | AO34: Not Started | AP34: Not Contacted
A35: LIVE-034 | B35: 31 | C35: P3 – Conditional / verify | D35: =ROUND(E35*0.35+F35*0.25+G35*0.15+H35*0.15+I35*0.05+J35*0.05,1) | E35: 85 | F35: 68 | G35: 75 | H35: 75 | I35: 20 | J35: 20 | K35: CoLLearn Education Technologies | L35: Operations Associate | M35: Startup operations / founder support / coordination | O35: Indeed JOBSEARCH_100698 | P35: Indeed public search token; not employer req ID | Q35: C – recent Indeed listing; apply link available through job board; confirm eligibility | R35: Posted 29 Sep 2026 (Indeed result) | S35: 46306 | T35: JP Nagar / Bengaluru (verify exact office) | U35: Not stated | V35: Full-time likely; verify | W35: Experience requirement not confirmed in retrieved result | X35: Not specified | Y35: Not disclosed | Z35: No reliable estimate found | AA35: Not disclosed | AB35: Not disclosed | AC35: Not disclosed | AD35: Not disclosed | AE35: Not disclosed | AF35: Not disclosed | AG35: Operations role at education technology startup; likely coordination/documentation based on current description, but verify full responsibilities on listing. | AH35: Event coordination, operations logistics, volunteer scheduling, spreadsheets and digital portfolio are transferable. | AI35: Confirm experience/degree requirements, direct employer link, pay and whether outbound sales/lead generation is part of the role. | AJ35: https://to.indeed.com/aa4cp98p99fs | AK35: https://in.indeed.com/jobs?q=CoLLearn+Operations+Associate&l=Bengaluru%2C+Karnataka | AL35: https://to.indeed.com/aa4cp98p99fs | AM35: Medium – Indeed listing | AN35: Review full job description; contact hiring team to verify duties, pay and current status. | AO35: Not Started | AP35: Not Contacted
A36: LIVE-041 | B36: 32 | C36: P3 – Conditional / verify | D36: =ROUND(E36*0.35+F36*0.25+G36*0.15+H36*0.15+I36*0.05+J36*0.05,1) | E36: 74 | F36: 90 | G36: 60 | H36: 75 | I36: 20 | J36: 20 | K36: Pearson India Education Services | L36: HR Operations Associate Intern | M36: HR shared services / operations internship | O36: Apna 1682511397 | P36: Public Apna job ID | Q36: C – board listing; check official Pearson careers / internship status | R36: Posted date not shown; returned in Apna fresher search 11 Oct 2026 | S36: 46306 | T36: Bengaluru – Cunningham Road address in listing | U36: On-site address listed; exact hybrid status not stated | V36: Internship | W36: Freshers only in job board details | X36: Degree requirements not fully specified in captured excerpt | Y36: Not disclosed | Z36: No reliable stipend benchmark found | AA36: Not disclosed | AB36: Not disclosed | AC36: Not disclosed | AD36: Not disclosed | AE36: Not disclosed | AF36: Duration / work hours need confirmation | AG36: HR operations intern role; listing describes exposure to a team, training and projects, but full HR tasks need review. | AH36: Administration, records, scheduling, documentation and Excel checks transfer. | AI36: Stipend/duration/current official listing not confirmed. It is an internship, not a permanent job. | AJ36: https://apna.co/job/bengaluru-bangalore/hr-operations-associate-intern-1682511397 | AK36: https://pearson.jobs/ | AL36: https://apna.co/job/bengaluru-bangalore/hr-operations-associate-intern-1682511397 | AM36: Medium – public listing; official portal must be matched | AN36: Check Pearson official career site; ask duration, stipend, weekly hours and PPO possibility. | AO36: Not Started | AP36: Not Contacted
A37: LIVE-018 | B37: 33 | C37: P3 – Conditional / verify | D37: =ROUND(E37*0.35+F37*0.25+G37*0.15+H37*0.15+I37*0.05+J37*0.05,1) | E37: 83 | F37: 53 | G37: 65 | H37: 100 | I37: 20 | J37: 50 | K37: Amazon | L37: Process Associate, AMXL FC | M37: Fulfilment centre / inventory / operations | N37: 10521256 | P37: Official Amazon job ID | Q37: B – official Amazon page indexed recently; re-open before applying | R37: Posted 29 Aug 2026; official page updated recently | S37: 46306 | T37: Bengaluru | U37: On-site / operations floor likely; exact schedule on page | V37: Full-time | W37: 1+ year Microsoft Office products/applications experience required | X37: High school/equivalent minimum; bachelor's degree preferred | Y37: Not disclosed | Z37: No reliable role-specific estimate verified | AA37: Not disclosed | AB37: Not disclosed | AC37: Amazon company-wide benefit page is conditional by role, country and job status; details not attached to job page | AD37: PTO and paid holidays referenced generically by Amazon; role-specific India policy must be confirmed | AE37: Transport/meal/cab not disclosed on posting | AF37: Flexible schedule/shift, including nights/weekends/holidays; role involves long periods standing/walking and lifting/pushing up to 49 lbs. | AG37: Daily floor operations, inbound/outbound and re-boxing, task allocation, quality checks, SOPs, KPI reporting and issue resolution. | AH37: Inventory/event operations and attention to detail transfer, and CV lists MS Office. | AI37: Explicit 1+ years Office experience required; the CV doesn't clearly evidence the duration. Physical demands and shift/weekend work are substantial. | AJ37: https://www.amazon.jobs/en/jobs/10521256/process-associate-amxl-fc | AK37: https://www.amazon.jobs/en/jobs/10521256/process-associate-amxl-fc | AL37: https://www.amazon.jobs/content/en/benefits | AM37: High – official job page has full description | AN37: Apply only if comfortable with site-floor duties, physical requirements and shift; verify the 1+ year Office requirement. | AO37: Not Started | AP37: Not Contacted
A38: LIVE-042 | B38: 34 | C38: P3 – Conditional / verify | D38: =ROUND(E38*0.35+F38*0.25+G38*0.15+H38*0.15+I38*0.05+J38*0.05,1) | E38: 73 | F38: 90 | G38: 60 | H38: 75 | I38: 20 | J38: 20 | K38: Deutsche Bank | L38: Human Resources Apprentice – 2026–2027 | M38: HR operations / apprenticeship | O38: Apna 1125222884 | P38: Public Apna job ID; official NATS requisition not verified | Q38: C – apprenticeship lead; verify Deutsche Bank/NATS registration is still open | R38: Posting date not displayed; returned in Apna fresher search 11 Oct 2026 | S38: 46306 | T38: Bengaluru (listing also mentions Mumbai/Pune) | U38: On-site/hybrid not stated | V38: 12-month apprenticeship | W38: Freshers only per public listing | X38: Graduate apprenticeship requirements must be checked on official NATS/Deutsche Bank portal | Y38: Stipend not disclosed in captured listing | Z38: No reliable public stipend amount verified | AA38: Not disclosed | AB38: Not disclosed | AC38: Not disclosed | AD38: Not disclosed | AE38: Not disclosed | AF38: Training schedule not stated | AG38: Formal apprenticeship with on-the-job HR learning and support for HR operations/initiatives. | AH38: Scheduling, records and operations coordination are transferable; formal HR exposure is a useful pathway. | AI38: Listing states no guarantee of permanent employment after 12-month apprenticeship. Verify age/pass-out year/NATS criteria, stipend and deadlines. | AJ38: https://apna.co/job/bengaluru-bangalore/human-resources-apprentice-1125222884 | AK38: https://careers.db.com/ | AL38: https://apna.co/job/bengaluru-bangalore/human-resources-apprentice-1125222884 | AM38: Medium – public job board; official apprenticeship number not verified | AN38: Search official DB careers and NATS for exact apprenticeship number; confirm 2026 BBA eligibility and stipend. | AO38: Not Started | AP38: Not Contacted
A39: LIVE-019 | B39: 35 | C39: P3 – Conditional / verify | D39: =ROUND(E39*0.35+F39*0.25+G39*0.15+H39*0.15+I39*0.05+J39*0.05,1) | E39: 78 | F39: 48 | G39: 82 | H39: 100 | I39: 20 | J39: 50 | K39: Amazon | L39: Process Associate, BLR7 Inbound | M39: Warehouse / inbound operations | N39: 10544311 | P39: Official Amazon job ID | Q39: B – official Amazon job-search result; confirm availability | R39: Posted 16 Sep 2026; updated 11 days before snapshot | S39: 46306 | T39: Bengaluru | U39: On-site / warehouse | V39: Full-time | W39: 1+ year Microsoft Office products/applications experience required | X39: High school/equivalent minimum; bachelor's degree may not be required | Y39: Not disclosed | Z39: No reliable role-specific estimate verified | AA39: Not disclosed | AB39: Not disclosed | AC39: Company-wide Amazon benefits page only; role/country/job-status dependent | AD39: Company-wide page refers to PTO and holidays; job-specific policy not shown | AE39: Not disclosed | AF39: Flexible shifts/weekends/nights/holidays; physical warehouse duties may apply | AG39: Inbound warehouse/process operations; basic qualifications resemble Amazon process associate jobs. | AH39: Inventory accuracy and operational coordination transfer. | AI39: Physical role and 1+ year Office requirement; validate actual requirements and working schedule. | AJ39: https://www.amazon.jobs/en/search?city%5B%5D=Bengaluru&distanceType=Mi&industry_experience=less_than_1_year&radius=24km&result_limit=10 | AK39: https://www.amazon.jobs/en/search?city%5B%5D=Bengaluru&distanceType=Mi&industry_experience=less_than_1_year&radius=24km&result_limit=10 | AL39: https://www.amazon.jobs/content/en/benefits | AM39: High official search source; detailed direct page not linked in this data capture | AN39: Search Amazon jobs by ID 10544311; check onsite work and physical conditions before applying. | AO39: Not Started | AP39: Not Contacted
A40: LIVE-040 | B40: 36 | C40: P3 – Conditional / verify | D40: =ROUND(E40*0.35+F40*0.25+G40*0.15+H40*0.15+I40*0.05+J40*0.05,1) | E40: 68 | F40: 85 | G40: 75 | H40: 70 | I40: 20 | J40: 20 | K40: Firstsource Solutions | L40: Customer Service Associate (CSA) | M40: Customer support / BPO operations | O40: Indeed JOBSEARCH_100688 | P40: Indeed public search token; not internal requisition | Q40: C – current Indeed result; confirm exact process, shift, and active hiring | R40: Posted 30 Sep 2026 (Indeed result) | S40: 46306 | T40: Bengaluru | U40: Not stated | V40: Full-time | W40: Fresher hiring referenced; exact job-specific eligibility to confirm | X40: Graduation/qualification not fully captured in current excerpt | Y40: Not disclosed | Z40: No reliable role-specific estimate found | AA40: Not disclosed | AB40: Not disclosed | AC40: Not disclosed on exact listing | AD40: Not disclosed | AE40: Transport/cab/meal not disclosed | AF40: Shift/process details need verification | AG40: Customer service associate process; full role duties and whether voice/non-voice/retention or cross-sell need to be checked. | AH40: Customer relations and structured communication are transferable. | AI40: Backup only: clarify whether role has sales, cross-sell, outbound calls, night shifts, transport and metrics before choosing. | AJ40: https://to.indeed.com/aay6yvz972hx | AK40: https://in.indeed.com/jobs?q=Firstsource+Customer+Service+Associate&l=Bengaluru%2C+Karnataka | AL40: https://to.indeed.com/aay6yvz972hx | AM40: Medium – Indeed listing | AN40: Apply only if income urgency outweighs preference for non-sales; ask whether chat/email or voice, and confirm any sales KPIs. | AO40: Not Started | AP40: Not Contacted
A41: LIVE-028 | B41: 37 | C41: P3 – Conditional / verify | D41: =ROUND(E41*0.35+F41*0.25+G41*0.15+H41*0.15+I41*0.05+J41*0.05,1) | E41: 77 | F41: 78 | G41: 60 | H41: 75 | I41: 20 | J41: 20 | K41: Altisource | L41: Associate – Granite | M41: Business / financial operations support | O41: Apna 1340046698 | P41: Public Apna job ID | Q41: C – job-board lead; official job title and details must be confirmed | R41: Posted date not shown; returned in Apna fresher search 11 Oct 2026 | S41: 46306 | T41: Bengaluru | U41: Not stated | V41: Full-time | W41: Freshers only per Apna listing | X41: Exact degree requirement not shown in retrieved excerpt | Y41: Not disclosed | Z41: No reliable role-specific estimate verified | AA41: Not disclosed | AB41: Not disclosed | AC41: Not disclosed on target role page | AD41: Not disclosed | AE41: Not disclosed | AF41: Not disclosed | AG41: Posting description mentions exposure to executives and financial strategy for business lines; full responsibilities must be checked. | AH41: Business administration, Excel/data validation, communication and AI/dashboard projects could be relevant if work is reporting/operations oriented. | AI41: Public listing text is incomplete; check whether role requires advanced finance/analytics skills or has sales/research targets; internal req unknown. | AJ41: https://apna.co/job/bengaluru-bangalore/associate-1340046698 | AK41: https://www.altisource.com/careers/ | AL41: https://apna.co/job/bengaluru-bangalore/associate-1340046698 | AM41: Medium-low – aggregator detail needs official confirmation | AN41: Read official job description before applying; get internal req and confirm day-to-day tasks plus CTC. | AO41: Not Started | AP41: Not Contacted
A42: LIVE-020 | B42: 38 | C42: P3 – Conditional / verify | D42: =ROUND(E42*0.35+F42*0.25+G42*0.15+H42*0.15+I42*0.05+J42*0.05,1) | E42: 77 | F42: 48 | G42: 65 | H42: 100 | I42: 20 | J42: 50 | K42: Amazon | L42: Process Associate, AMXL 3P FC – North | M42: Fulfilment centre / inventory operations | N42: 10521271 | P42: Official Amazon job ID | Q42: B/C – official Amazon search result; recheck current job state | R42: Posted 30 Aug 2026; updated 11 days before snapshot | S42: 46306 | T42: Bengaluru | U42: On-site / fulfilment centre | V42: Full-time | W42: 1+ year Microsoft Office products/applications experience required | X42: High school/equivalent minimum; bachelor's degree preferred | Y42: Not disclosed | Z42: No reliable role-specific estimate verified | AA42: Not disclosed | AB42: Not disclosed | AC42: Amazon company-wide benefits page only; India role eligibility must be confirmed | AD42: Generic Amazon PTO/holiday policy; exact India terms not listed in vacancy | AE42: Not disclosed | AF42: Shift/weekend/holiday and physical demands likely; confirm full listing | AG42: Fulfilment centre process operations; role-specific detailed responsibilities should be checked on Amazon portal. | AH42: Inventory and event operations can support this pivot. | AI42: 1+ year Office requirement and physical/shift demands must be checked. | AJ42: https://www.amazon.jobs/en/search?city%5B%5D=Bengaluru&distanceType=Mi&industry_experience=less_than_1_year&radius=24km&result_limit=10 | AK42: https://www.amazon.jobs/en/search?city%5B%5D=Bengaluru&distanceType=Mi&industry_experience=less_than_1_year&radius=24km&result_limit=10 | AL42: https://www.amazon.jobs/content/en/benefits | AM42: High official search listing; limited job details in indexed snippet | AN42: Search Amazon jobs by ID 10521271; skip if the 1+ year Office requirement cannot be supported. | AO42: Not Started | AP42: Not Contacted
A43: LIVE-038 | B43: 39 | C43: P3 – Conditional / verify | D43: =ROUND(E43*0.35+F43*0.25+G43*0.15+H43*0.15+I43*0.05+J43*0.05,1) | E43: 82 | F43: 60 | G43: 65 | H43: 75 | I43: 20 | J43: 20 | K43: Integraminds | L43: Founder’s Office Associate | M43: Startup operations / founder's office | O43: Indeed JOBSEARCH_100782 | P43: Indeed public search token; not employer req ID | Q43: C – recently indexed startup listing; official careers page/current status not validated | R43: Posted 18 Sep 2026 (Indeed result) | S43: 46306 | T43: Bengaluru | U43: Not stated | V43: Full-time assumed from title; verify | W43: Not confirmed in retrieved source | X43: Not confirmed | Y43: Not disclosed | Z43: No reliable estimate found | AA43: Not disclosed | AB43: Not disclosed | AC43: Not disclosed | AD43: Not disclosed | AE43: Not disclosed | AF43: Not disclosed | AG43: The listing overview describes an execution-focused Founder’s Office role; full daily responsibilities and business model need validation. | AH43: AI workflow prototypes, presentations, event logistics, data checking and cross-functional coordination may be transferable. | AI43: Founder-office roles can mix operations with sales, research and long hours; confirm actual responsibilities, pay and founder working style. | AJ43: https://to.indeed.com/aaklwxdc2btp | AK43: https://in.indeed.com/jobs?q=Integraminds+Founder%27s+Office+Associate&l=Bengaluru%2C+Karnataka | AL43: https://to.indeed.com/aaklwxdc2btp | AM43: Medium-low – Indeed role listing; full details need review | AN43: Read full posting, verify company/careers page and ask whether role is 70%+ non-sales operations before applying. | AO43: Not Started | AP43: Not Contacted
A44: LIVE-021 | B44: 40 | C44: P3 – Conditional / verify | D44: =ROUND(E44*0.35+F44*0.25+G44*0.15+H44*0.15+I44*0.05+J44*0.05,1) | E44: 61 | F44: 55 | G44: 60 | H44: 100 | I44: 20 | J44: 50 | K44: Amazon | L44: Associate, Quality Services – Auto Software (Smart Vehicles) | M44: Quality services / software-adjacent operations | N44: 10531849 | P44: Official Amazon job ID | Q44: C – official Amazon search result; technical scope needs confirmation | R44: Posted 8 Sep 2026; updated about 16 days before snapshot | S44: 46306 | T44: Bengaluru | U44: Not disclosed | V44: Full-time | W44: Experience requirement not shown in result snippet | X44: Bachelor’s degree; knowledge of QA methodology and tools | Y44: Not disclosed | Z44: No reliable role-specific estimate verified | AA44: Not disclosed | AB44: Not disclosed | AC44: Amazon company-wide benefits page only; role-specific package not disclosed | AD44: Generic PTO and paid holidays; exact India policy not in listing | AE44: Not disclosed | AF44: Not disclosed | AG44: Quality services role on Smart Vehicles / Auto Software team; full technical content needs review. | AH44: CV data-quality work is somewhat transferable. | AI44: Auto Software may require technical testing knowledge beyond the CV. Lower fit than business operations positions. | AJ44: https://www.amazon.jobs/en/search?city%5B%5D=Bengaluru&distanceType=Mi&industry_experience=less_than_1_year&radius=24km&result_limit=10 | AK44: https://www.amazon.jobs/en/search?city%5B%5D=Bengaluru&distanceType=Mi&industry_experience=less_than_1_year&radius=24km&result_limit=10 | AL44: https://www.amazon.jobs/content/en/benefits | AM44: High official search result; fit not confirmed | AN44: Only pursue after reading full posting and checking if non-technical QA tasks are accepted. | AO44: Not Started | AP44: Not Contacted
A45: LIVE-011 | B45: 41 | C45: P4 – Hold / weak fit | D45: =ROUND(E45*0.35+F45*0.25+G45*0.15+H45*0.15+I45*0.05+J45*0.05,1) | E45: 80 | F45: 35 | G45: 92 | H45: 100 | I45: 50 | J45: 55 | K45: Accenture | L45: Procure to Pay Operations New Associate – Invoice Processing | M45: P2P / accounts payable support | N45: AIOC-S01654688 | P45: Official Accenture requisition ID | Q45: D – recent indexed listing but degree requirement appears narrowly BCom-only | R45: Posting date not shown; indexed two days before snapshot | S45: 46306 | T45: Bengaluru | U45: Rotational shift possible | V45: Full-time | W45: 0–1 years | X45: BCom (as stated) | Y45: Not disclosed by employer | Z45: ₹2–5 LPA broad external estimates for related roles; not an offer | AA45: Not disclosed | AB45: Not disclosed | AC45: Company-wide medical cover described; exact role terms unknown | AD45: Company-wide PTO policy; details at offer stage | AE45: Not disclosed | AF45: Rotational shifts may be required | AG45: Invoice processing / procurement-to-pay finance operations. | AH45: Transferable spreadsheet/data checking and record-control evidence. | AI45: Explicit BCom qualification appears to be a mismatch with BBA International Business. Do not prioritise unless HR confirms acceptance. | AJ45: https://www.accenture.com/in-en/careers/jobdetails?id=AIOC-S01654688_en | AK45: https://www.accenture.com/in-en/careers/jobdetails?id=AIOC-S01654688_en | AL45: https://www.glassdoor.co.in/Salary/Accenture-Procure-to-Pay-Operations-New-Associate-Salaries-E4138_D_KO10%2C49.htm | AM45: High – qualification mismatch risk | AN45: Hold; ask recruitment if a BBA International Business degree is accepted before applying. | AO45: Not Started | AP45: Not Contacted
A46: LIVE-039 | B46: 42 | C46: P4 – Hold / weak fit | D46: =ROUND(E46*0.35+F46*0.25+G46*0.15+H46*0.15+I46*0.05+J46*0.05,1) | E46: 80 | F46: 85 | G46: 45 | H46: 70 | I46: 20 | J46: 20 | K46: thinkquestlab Pvt Ltd | L46: Operations Associate and Office Admin – Fresher | M46: Office operations / administration | O46: Indeed JOBSEARCH_100785 | P46: Indeed public search token; not employer requisition | Q46: D – walk-in date/availability may be stale; call or reopen before travelling | R46: Posted 17 Sep 2026; listing mentions a walk-in drive, timing should be rechecked | S46: 46306 | T46: Bengaluru | U46: On-site | V46: Full-time | W46: Fresher in title; confirm exact experience rules | X46: Not fully specified | Y46: Not disclosed | Z46: No reliable estimate found | AA46: Not disclosed | AB46: Not disclosed | AC46: Not disclosed | AD46: Not disclosed | AE46: Travel to interview not reimbursed unless employer confirms | AF46: Work hours/weekly off not captured | AG46: Office administration and operations support; full responsibilities need review in current posting. | AH46: Office tools, coordination, schedules, documentation and computer proficiency are relevant. | AI46: Do not travel to a walk-in without confirming date, office address, employer identity, salary and current vacancy. | AJ46: https://to.indeed.com/aahzbvfgpfns | AK46: https://in.indeed.com/jobs?q=thinkquestlab+Operations+Associate+Office+Admin&l=Bengaluru%2C+Karnataka | AL46: https://to.indeed.com/aahzbvfgpfns | AM46: Medium-low – aggregator lead with walk-in uncertainty | AN46: Call/email to reconfirm whether vacancy and walk-in are still open before proceeding. | AO46: Not Started | AP46: Not Contacted
A47: LIVE-043 | B47: 43 | C47: P4 – Hold / weak fit | D47: =ROUND(E47*0.35+F47*0.25+G47*0.15+H47*0.15+I47*0.05+J47*0.05,1) | E47: 73 | F47: 45 | G47: 92 | H47: 70 | I47: 20 | J47: 20 | K47: Goldman Sachs | L47: Corporate Planning & Management – Associate, Risk Governance | M47: Risk governance / procurement operations | O47: Indeed JOBSEARCH_100797 | P47: Indeed public search token; Goldman internal requisition not captured | Q47: C – recent Indeed listing, but experience level/degree not confirmed; direct GS requisition must be found | R47: Posted 9 Oct 2026 (Indeed result) | S47: 46306 | T47: Bengaluru | U47: Not stated | V47: Full-time | W47: Experience requirement unknown in captured snippet | X47: Not specified in retrieved snippet | Y47: Not disclosed | Z47: No reliable role-specific estimate verified | AA47: Not disclosed | AB47: Not disclosed | AC47: No role-specific benefits in listing; official GS benefits page needs research | AD47: Not disclosed | AE47: Not disclosed | AF47: Not disclosed | AG47: Job text says Lifecycle Management team sits within Global Procurement under Corporate Planning & Management; analytical mindset mentioned. | AH47: International Business background, research, documentation and data checking could be relevant if entry-level criteria permit. | AI47: Role may be aimed at experienced candidate; don't treat title as fresher role without full posting. Public Indeed token is not GS job ID. | AJ47: https://to.indeed.com/aajkwfm9zhfn | AK47: https://www.goldmansachs.com/careers/ | AL47: https://to.indeed.com/aajkwfm9zhfn | AM47: Medium-low – fresh listing but exact criteria missing | AN47: Find official GS Careers record for same title and confirm years of experience before referral. | AO47: Not Started | AP47: Not Contacted

Sheet Comp & Benefits
A1: COMPENSATION & BENEFITS LEDGER | DISCLOSURE FIRST
A2: Research snapshot 11 Oct 2026. Blank/missing benefits mean NOT DISCLOSED, not zero and not included in an offer. Employer-stated pay is separated from external estimates. Verify every item against the written offer and benefits guide.
A4: Record ID | B4: Rank | C4: Company | D4: Role | E4: Official Requisition ID | F4: Public Listing ID | G4: ID Type | H4: Employer-Stated Annual Salary / CTC | I4: Pay Break-up: Fixed / Variable | J4: External Benchmark (not offer) | K4: Annual Bonus / Incentive / Stock | L4: Joining Bonus | M4: Medical / Health Insurance | N4: Life / Accident Insurance | O4: PF / Gratuity / Retirement | P4: Annual Leave / Sick / Casual Leave | Q4: Public Holidays | R4: Weekly Off / Work Pattern | S4: Shift / Working Hours | T4: Transport / Cab / Travel | U4: Meals / Relocation / Other Perks | V4: Openings / Applicants / Deadline | W4: Disclosure Status | X4: Benefits / Compensation Source URL | Y4: What to Ask Recruiter
A5: LIVE-035 | B5: 1 | C5: Nathaniel School of Music | D5: Operations & Admin Executive (Education) – Fresher | E5: Not found / not applicable | F5: 1791182216 | G5: Internshala listing reference/slug suffix; not internal requisition | H5: ₹3,00,000–₹4,20,000/year listed; salary breakup not shown | I5: Fixed/variable split not stated by employer | J5: Advertised annual salary range; verify if employer calls it CTC and what is fixed | K5: No bonus/variable pay disclosed | L5: No joining bonus disclosed | M5: No health/insurance details disclosed | N5: See employer benefits source; coverage/eligibility must be confirmed | O5: Not disclosed unless employer benefits policy confirms; check offer/benefits guide | P5: Leave not specified | Q5: Not disclosed in reviewed job listing | R5: 6 days/week stated by employer | S5: Company says six days/week; exact role hours not stated | T5: Travel/cab/meal not disclosed | U5: Only perks explicitly listed in the posting; if none stated, treat as not disclosed | V5: One opening stated; 44 applicants at retrieval; informal dress code is the only listed perk.; Posted 6 days ago; apply by 4 Nov 2026; 44 applicants at detail retrieval | W5: Medium-high – detailed listing with deadline, pay, duties and BBA fit | X5: https://internshala.com/job/detail/fresher-operations-admin-executive-education-job-in-bangalore-at-nathaniel-school-of-music1791182216/ | Y5: Ask for annual CTC and fixed gross; monthly take-home; variable pay; joining/retention bonus; insurance start date and dependants; PF/gratuity; leave and holidays; cab/transport; meal allowance; shift differential; weekly off; probation; notice period; appraisal; relocation/travel reimbursement.
A6: LIVE-003 | B6: 2 | C6: Accenture | D6: Procurement Practice New Associate | E6: AIOC-S01667387 | F6: Not found | G6: Official Accenture requisition ID | H6: Not disclosed by employer | I6: Fixed/variable split not stated by employer | J6: ₹3–5 LPA Glassdoor estimate for a related Procurement Operations New Associate Bengaluru posting; estimate only, not an offer | K6: Company-wide bonus programmes and an employee share purchase plan are described on the benefits page; no role-specific amount/eligibility disclosed. | L6: Not disclosed | M6: Accenture India benefit page describes medical coverage; exact role/coverage terms not shown | N6: See employer benefits source; coverage/eligibility must be confirmed | O6: Not disclosed unless employer benefits policy confirms; check offer/benefits guide | P6: Company page says state-based PTO including earned/sick/casual leave and 10 public holidays | Q6: 10 public holidays on Accenture company-wide benefits page; role-specific eligibility should be confirmed | R6: Not disclosed unless noted in working-hours field | S6: Rotational shifts may be required | T6: Not disclosed for this opening | U6: Only perks explicitly listed in the posting; if none stated, treat as not disclosed | V6: Any Graduation; 0–1 years accepted in official listing; Posting date not shown; official listing crawled 11 Oct 2026 | W6: High – official role page and matching third-party salary estimate | X6: https://www.accenture.com/in-en/careers/local/benefits | Y6: Ask for annual CTC and fixed gross; monthly take-home; variable pay; joining/retention bonus; insurance start date and dependants; PF/gratuity; leave and holidays; cab/transport; meal allowance; shift differential; weekly off; probation; notice period; appraisal; relocation/travel reimbursement.
A7: LIVE-005 | B7: 3 | C7: Accenture | D7: Procurement Practice New Associate | E7: AIOC-S01664045 | F7: Not found | G7: Official Accenture requisition ID | H7: Not disclosed by employer | I7: Fixed/variable split not stated by employer | J7: ₹3–5 LPA estimated for a closely related Accenture procurement new-associate role (Glassdoor; not official CTC) | K7: Company-wide bonus programmes and an employee share purchase plan are described on the benefits page; no role-specific amount/eligibility disclosed. | L7: Not disclosed | M7: Medical coverage is described company-wide; role specifics unknown | N7: See employer benefits source; coverage/eligibility must be confirmed | O7: Not disclosed unless employer benefits policy confirms; check offer/benefits guide | P7: State-based PTO; 10 public holidays in company-wide policy | Q7: 10 public holidays on Accenture company-wide benefits page; role-specific eligibility should be confirmed | R7: Not disclosed unless noted in working-hours field | S7: Rotational shifts may be required | T7: Not disclosed | U7: Only perks explicitly listed in the posting; if none stated, treat as not disclosed | V7: Any Graduation; 0–1 years stated; Posting date not shown; official listing crawled 10 Oct 2026 | W7: High – official role page; third-party estimate is adjacent role | X7: https://www.accenture.com/in-en/careers/local/benefits | Y7: Ask for annual CTC and fixed gross; monthly take-home; variable pay; joining/retention bonus; insurance start date and dependants; PF/gratuity; leave and holidays; cab/transport; meal allowance; shift differential; weekly off; probation; notice period; appraisal; relocation/travel reimbursement.
A8: LIVE-024 | B8: 4 | C8: SharePal | D8: Associate – Purchase – Fresher | E8: Not found / not applicable | F8: 1790684619 | G8: Internshala listing reference/slug suffix; not an internal req ID | H8: ₹4,00,000–₹5,00,000/year listed; salary break-up not provided | I8: Fixed/variable split not stated by employer | J8: Employer-advertised annual pay range; not independently verified as CTC | K8: No variable/bonus detail disclosed | L8: No joining bonus disclosed | M8: No health/insurance detail listed | N8: See employer benefits source; coverage/eligibility must be confirmed | O8: Not disclosed unless employer benefits policy confirms; check offer/benefits guide | P8: No leave/holiday detail listed | Q8: Not disclosed in reviewed job listing | R8: Not disclosed unless noted in working-hours field | S8: Workday/hours/weekly off not disclosed | T8: No transport/travel allowance listed | U8: Only perks explicitly listed in the posting; if none stated, treat as not disclosed | V8: Four openings indicated in the listing; 252 applicants at retrieval.; Posted 1 week ago; apply-by 29 Oct 2026; 252 applicants at detail retrieval | W8: Medium-high – detailed internship-platform listing with salary and deadline | X8: https://internshala.com/job/detail/fresher-associate-purchase-job-in-bangalore-at-sharepal1790684619/ | Y8: Ask for annual CTC and fixed gross; monthly take-home; variable pay; joining/retention bonus; insurance start date and dependants; PF/gratuity; leave and holidays; cab/transport; meal allowance; shift differential; weekly off; probation; notice period; appraisal; relocation/travel reimbursement.
